{"Siri":{"version":"1.3","ServiceDelivery":{"ResponseTimestamp":1479233250874,"ProducerRef":{"value":"HSL"},"Status":true,"MoreData":false,"VehicleMonitoringDelivery":[{"version":"1.3","ResponseTimestamp":1479233250874,"Status":true,"VehicleActivity":[{"ValidUntilTime":1479233266151,"RecordedAtTime":1479233236151,"MonitoredVehicleJourney":{"LineRef":{"value":"4611"},"DirectionRef":{"value":"2"},"FramedVehicleJourneyRef":{"DataFrameRef":{"value":"2016-11-15"},"DatedVehicleJourneyRef":"1924"},"OperatorRef":{"value":"HSL"},"Monitored":true,"VehicleLocation":{"Longitude":24.95607,"Latitude":60.19481},"Delay":242,"MonitoredCall":{"StopPointRef":"1220111"},"VehicleRef":{"value":"1002"}}},{"ValidUntilTime":1479233254307,"RecordedAtTime":1479233224307,"MonitoredVehicleJourney":{"LineRef":{"value":"4611"},"DirectionRef":{"value":"1"},"FramedVehicleJourneyRef":{"DataFrameRef":{"value":"2016-11-15"},"DatedVehicleJourneyRef":"1915"},"OperatorRef":{"value":"HSL"},"Monitored":true,"VehicleLocation":{"Longitude":25.03075,"Latitude":60.28928},"Delay":374,"MonitoredCall":{"StopPointRef":"4610219"},"VehicleRef":{"value":"1003"}}},{"ValidUntilTime":1479233241783,"RecordedAtTime":1479233211783,"MonitoredVehicleJourney":{"LineRef":{"value":"1070T"},"DirectionRef":{"value":"2"},"FramedVehicleJourneyRef":{"DataFrameRef":{"value":"2016-11-15"},"DatedVehicleJourneyRef":"1954"},"OperatorRef":{"value":"HSL"},"Monitored":true,"VehicleLocation":{"Longitude":24.98358,"Latitude":60.26407},"Delay":172,"MonitoredCall":{"StopPointRef":"1391113"},"VehicleRef":{"value":"1004"}}},{"ValidUntilTime":1479233252415,"RecordedAtTime":1479233222415,"MonitoredVehicleJourney":{"LineRef":{"value":"4611"},"DirectionRef":{"value":"2"},"FramedVehicleJourneyRef":{"DataFrameRef":{"value":"2016-11-15"},"DatedVehicleJourneyRef":"1944"},"OperatorRef":{"value":"HSL"},"Monitored":true,"VehicleLocation":{"Longitude":24.98964,"Latitude":60.27065},"Delay":248,"MonitoredCall":{"StopPointRef":"1401102"},"VehicleRef":{"value":"1006"}}},{"ValidUntilTime":1479233274041,"RecordedAtTime":1479233244041,"MonitoredVehicleJourney":{"LineRef":{"value":"1070T"},"DirectionRef":{"value":"2"},"FramedVehicleJourneyRef":{"DataFrameRef":{"value":"2016-11-15"},"DatedVehicleJourneyRef":"1934"},"OperatorRef":{"value":"HSL"},"Monitored":true,"VehicleLocation":{"Longitude":24.96165,"Latitude":60.19776},"Delay":0,"MonitoredCall":{"StopPointRef":"1220128"},"VehicleRef":{"value":"1008"}}},{"ValidUntilTime":1479233246832,"RecordedAtTime":1479233216832,"MonitoredVehicleJourney":{"LineRef":{"value":"4611"},"DirectionRef":{"value":"1"},"FramedVehicleJourneyRef":{"DataFrameRef":{"value":"2016-11-15"},"DatedVehicleJourneyRef":"1945"},"OperatorRef":{"value":"HSL"},"Monitored":true,"VehicleLocation":{"Longitude":24.94816,"Latitude":60.23991},"Delay":114,"MonitoredCall":{"StopPointRef":"1342198"},"VehicleRef":{"value":"1010"}}},{"ValidUntilTime":1479233232951,"RecordedAtTime":1479233202951,"MonitoredVehicleJourney":{"LineRef":{"value":"1018"},"DirectionRef":{"value":"1"},"FramedVehicleJourneyRef":{"DataFrameRef":{"value":"2016-11-15"},"DatedVehicleJourneyRef":"1944"},"OperatorRef":{"value":"HSL"},"Monitored":true,"VehicleLocation":{"Longitude":24.91094,"Latitude":60.1894},"Delay":212,"MonitoredCall":{"StopPointRef":"1150109"},"VehicleRef":{"value":"1103"}}},{"ValidUntilTime":1479233258234,"RecordedAtTime":1479233228234,"MonitoredVehicleJourney":{"LineRef":{"value":"1014"},"DirectionRef":{"value":"1"},"FramedVehicleJourneyRef":{"DataFrameRef":{"value":"2016-11-15"},"DatedVehicleJourneyRef":"2007"},"OperatorRef":{"value":"HSL"},"Monitored":true,"VehicleLocation":{"Longitude":24.92336,"Latitude":60.14824},"Delay":0,"MonitoredCall":{"StopPointRef":"1204101"},"VehicleRef":{"value":"1105"}}},{"ValidUntilTime":1479233274066,"RecordedAtTime":1479233244066,"MonitoredVehicleJourney":{"LineRef":{"value":"4415"},"DirectionRef":{"value":"1"},"FramedVehicleJourneyRef":{"DataFrameRef":{"value":"2016-11-15"},"DatedVehicleJourneyRef":"1952"},"OperatorRef":{"value":"HSL"},"Monitored":true,"VehicleLocation":{"Longitude":24.8992,"Latitude":60.2051},"Delay":130,"MonitoredCall":{"StopPointRef":"1160206"},"VehicleRef":{"value":"1122"}}},{"ValidUntilTime":1479233258634,"RecordedAtTime":1479233228634,"MonitoredVehicleJourney":{"LineRef":{"value":"1018"},"DirectionRef":{"value":"2"},"FramedVehicleJourneyRef":{"DataFrameRef":{"value":"2016-11-15"},"DatedVehicleJourneyRef":"1944"},"OperatorRef":{"value":"HSL"},"Monitored":true,"VehicleLocation":{"Longitude":24.92218,"Latitude":60.17972},"Delay":126,"MonitoredCall":{"StopPointRef":"1140103"},"VehicleRef":{"value":"1123"}}},{"ValidUntilTime":1479233223476,"RecordedAtTime":1479233193476,"MonitoredVehicleJourney":{"LineRef":{"value":"4614"},"DirectionRef":{"value":"1"},"FramedVehicleJourneyRef":{"DataFrameRef":{"value":"2016-11-15"},"DatedVehicleJourneyRef":"1940"},"OperatorRef":{"value":"HSL"},"Monitored":true,"VehicleLocation":{"Longitude":24.96518,"Latitude":60.2689},"Delay":0,"MonitoredCall":{"StopPointRef":"4500218"},"VehicleRef":{"value":"1132"}}},{"ValidUntilTime":1479233265662,"RecordedAtTime":1479233235662,"MonitoredVehicleJourney":{"LineRef":{"value":"1039"},"DirectionRef":{"value":"2"},"FramedVehicleJourneyRef":{"DataFrameRef":{"value":"2016-11-15"},"DatedVehicleJourneyRef":"1942"},"OperatorRef":{"value":"HSL"},"Monitored":true,"VehicleLocation":{"Longitude":24.88139,"Latitude":60.20304},"Delay":24,"MonitoredCall":{"StopPointRef":"1301158"},"VehicleRef":{"value":"1207"}}},{"ValidUntilTime":1479233277411,"RecordedAtTime":1479233247411,"MonitoredVehicleJourney":{"LineRef":{"value":"1075"},"DirectionRef":{"value":"1"},"FramedVehicleJourneyRef":{"DataFrameRef":{"value":"2016-11-15"},"DatedVehicleJourneyRef":"1954"},"OperatorRef":{"value":"HSL"},"Monitored":true,"VehicleLocation":{"Longitude":24.96182,"Latitude":60.19822},"Delay":140,"MonitoredCall":{"StopPointRef":"1220105"},"VehicleRef":{"value":"1209"}}},{"ValidUntilTime":1479233275354,"RecordedAtTime":1479233245354,"MonitoredVehicleJourney":{"LineRef":{"value":"1075"},"DirectionRef":{"value":"1"},"FramedVehicleJourneyRef":{"DataFrameRef":{"value":"2016-11-15"},"DatedVehicleJourneyRef":"2015"},"OperatorRef":{"value":"HSL"},"Monitored":true,"VehicleLocation":{"Longitude":24.9429,"Latitude":60.17166},"MonitoredCall":{},"VehicleRef":{"value":"1212"}}},{"ValidUntilTime":1479233265174,"RecordedAtTime":1479233235174,"MonitoredVehicleJourney":{"LineRef":{"value":"1077"},"DirectionRef":{"value":"1"},"FramedVehicleJourneyRef":{"DataFrameRef":{"value":"2016-11-15"},"DatedVehicleJourneyRef":"2006"},"OperatorRef":{"value":"HSL"},"Monitored":true,"VehicleLocation":{"Longitude":24.94346,"Latitude":60.17069},"Delay":60,"MonitoredCall":{"StopPointRef":"1020105"},"VehicleRef":{"value":"1214"}}},{"ValidUntilTime":1479233271246,"RecordedAtTime":1479233241246,"MonitoredVehicleJourney":{"LineRef":{"value":"1075"},"DirectionRef":{"value":"1"},"FramedVehicleJourneyRef":{"DataFrameRef":{"value":"2016-11-15"},"DatedVehicleJourneyRef":"1933"},"OperatorRef":{"value":"HSL"},"Monitored":true,"VehicleLocation":{"Longitude":25.06321,"Latitude":60.26988},"Delay":0,"MonitoredCall":{"StopPointRef":"1411119"},"VehicleRef":{"value":"1215"}}},{"ValidUntilTime":1479233239304,"RecordedAtTime":1479233209304,"MonitoredVehicleJourney":{"LineRef":{"value":"1075"},"DirectionRef":{"value":"2"},"FramedVehicleJourneyRef":{"DataFrameRef":{"value":"2016-11-15"},"DatedVehicleJourneyRef":"2002"},"OperatorRef":{"value":"HSL"},"Monitored":true,"VehicleLocation":{"Longitude":25.05895,"Latitude":60.27013},"Delay":36,"MonitoredCall":{"StopPointRef":"1412120"},"VehicleRef":{"value":"1216"}}},{"ValidUntilTime":1479233260229,"RecordedAtTime":1479233230229,"MonitoredVehicleJourney":{"LineRef":{"value":"4614"},"DirectionRef":{"value":"1"},"FramedVehicleJourneyRef":{"DataFrameRef":{"value":"2016-11-15"},"DatedVehicleJourneyRef":"2010"},"OperatorRef":{"value":"HSL"},"Monitored":true,"VehicleLocation":{"Longitude":24.94307,"Latitude":60.17152},"Delay":0,"MonitoredCall":{"StopPointRef":"1020204"},"VehicleRef":{"value":"1219"}}},{"ValidUntilTime":1479233273147,"RecordedAtTime":1479233243147,"MonitoredVehicleJourney":{"LineRef":{"value":"1039"},"DirectionRef":{"value":"2"},"FramedVehicleJourneyRef":{"DataFrameRef":{"value":"2016-11-15"},"DatedVehicleJourneyRef":"1922"},"OperatorRef":{"value":"HSL"},"Monitored":true,"VehicleLocation":{"Longitude":24.92882,"Latitude":60.16868},"Delay":52,"MonitoredCall":{"StopPointRef":"1040107"},"VehicleRef":{"value":"1302"}}},{"ValidUntilTime":1479233259803,"RecordedAtTime":1479233229803,"MonitoredVehicleJourney":{"LineRef":{"value":"2550"},"DirectionRef":{"value":"1"},"FramedVehicleJourneyRef":{"DataFrameRef":{"value":"2016-11-15"},"DatedVehicleJourneyRef":"2001"},"OperatorRef":{"value":"HSL"},"Monitored":true,"VehicleLocation":{"Longitude":25.03464,"Latitude":60.22132},"Delay":0,"MonitoredCall":{"StopPointRef":"1362112"},"VehicleRef":{"value":"1305"}}},{"ValidUntilTime":1479233252907,"RecordedAtTime":1479233222907,"MonitoredVehicleJourney":{"LineRef":{"value":"2550"},"DirectionRef":{"value":"2"},"FramedVehicleJourneyRef":{"DataFrameRef":{"value":"2016-11-15"},"DatedVehicleJourneyRef":"1956"},"OperatorRef":{"value":"HSL"},"Monitored":true,"VehicleLocation":{"Longitude":24.80901,"Latitude":60.18709},"Delay":0,"MonitoredCall":{"StopPointRef":"2222268"},"VehicleRef":{"value":"1307"}}},{"ValidUntilTime":1479233275232,"RecordedAtTime":1479233245232,"MonitoredVehicleJourney":{"LineRef":{"value":"2550"},"DirectionRef":{"value":"2"},"FramedVehicleJourneyRef":{"DataFrameRef":{"value":"2016-11-15"},"DatedVehicleJourneyRef":"1916"},"OperatorRef":{"value":"HSL"},"Monitored":true,"VehicleLocation":{"Longitude":25.03609,"Latitude":60.22104},"Delay":102,"MonitoredCall":{"StopPointRef":"1454121"},"VehicleRef":{"value":"1310"}}},{"ValidUntilTime":1479233270339,"RecordedAtTime":1479233240339,"MonitoredVehicleJourney":{"LineRef":{"value":"2550"},"DirectionRef":{"value":"1"},"FramedVehicleJourneyRef":{"DataFrameRef":{"value":"2016-11-15"},"DatedVehicleJourneyRef":"1941"},"OperatorRef":{"value":"HSL"},"Monitored":true,"VehicleLocation":{"Longitude":24.91569,"Latitude":60.22977},"Delay":162,"MonitoredCall":{"StopPointRef":"1281160"},"VehicleRef":{"value":"1311"}}},{"ValidUntilTime":1479233268837,"RecordedAtTime":1479233238837,"MonitoredVehicleJourney":{"LineRef":{"value":"2550"},"DirectionRef":{"value":"2"},"FramedVehicleJourneyRef":{"DataFrameRef":{"value":"2016-11-15"},"DatedVehicleJourneyRef":"1906"},"OperatorRef":{"value":"HSL"},"Monitored":true,"VehicleLocation":{"Longitude":25.07506,"Latitude":60.20992},"Delay":334,"MonitoredCall":{"StopPointRef":"1453214"},"VehicleRef":{"value":"1312"}}},{"ValidUntilTime":1479233238887,"RecordedAtTime":1479233208887,"MonitoredVehicleJourney":{"LineRef":{"value":"2550"},"DirectionRef":{"value":"1"},"FramedVehicleJourneyRef":{"DataFrameRef":{"value":"2016-11-15"},"DatedVehicleJourneyRef":"1834"},"OperatorRef":{"value":"HSL"},"Monitored":true,"VehicleLocation":{"Longitude":24.90356,"Latitude":60.20766},"Delay":510,"MonitoredCall":{"StopPointRef":"2231213"},"VehicleRef":{"value":"1317"}}},{"ValidUntilTime":1479233261937,"RecordedAtTime":1479233231937,"MonitoredVehicleJourney":{"LineRef":{"value":"2550"},"DirectionRef":{"value":"1"},"FramedVehicleJourneyRef":{"DataFrameRef":{"value":"2016-11-15"},"DatedVehicleJourneyRef":"2031"},"OperatorRef":{"value":"HSL"},"Monitored":true,"VehicleLocation":{"Longitude":25.07778,"Latitude":60.21042},"MonitoredCall":{},"VehicleRef":{"value":"1321"}}},{"ValidUntilTime":1479233273140,"RecordedAtTime":1479233243140,"MonitoredVehicleJourney":{"LineRef":{"value":"4615"},"DirectionRef":{"value":"1"},"FramedVehicleJourneyRef":{"DataFrameRef":{"value":"2016-11-15"},"DatedVehicleJourneyRef":"1955"},"OperatorRef":{"value":"HSL"},"Monitored":true,"VehicleLocation":{"Longitude":24.9491,"Latitude":60.19781},"Delay":14,"MonitoredCall":{"StopPointRef":"1220207"},"VehicleRef":{"value":"1323"}}},{"ValidUntilTime":1479233250303,"RecordedAtTime":1479233220303,"MonitoredVehicleJourney":{"LineRef":{"value":"2550"},"DirectionRef":{"value":"2"},"FramedVehicleJourneyRef":{"DataFrameRef":{"value":"2016-11-15"},"DatedVehicleJourneyRef":"1926"},"OperatorRef":{"value":"HSL"},"Monitored":true,"VehicleLocation":{"Longitude":24.96841,"Latitude":60.22886},"Delay":0,"MonitoredCall":{"StopPointRef":"1285104"},"VehicleRef":{"value":"1325"}}},{"ValidUntilTime":1479233238898,"RecordedAtTime":1479233208898,"MonitoredVehicleJourney":{"LineRef":{"value":"2550"},"DirectionRef":{"value":"1"},"FramedVehicleJourneyRef":{"DataFrameRef":{"value":"2016-11-15"},"DatedVehicleJourneyRef":"1951"},"OperatorRef":{"value":"HSL"},"Monitored":true,"VehicleLocation":{"Longitude":24.9753,"Latitude":60.23125},"Delay":102,"MonitoredCall":{"StopPointRef":"1285101"},"VehicleRef":{"value":"1328"}}},{"ValidUntilTime":1479233249526,"RecordedAtTime":1479233219526,"MonitoredVehicleJourney":{"LineRef":{"value":"2550"},"DirectionRef":{"value":"1"},"FramedVehicleJourneyRef":{"DataFrameRef":{"value":"2016-11-15"},"DatedVehicleJourneyRef":"1911"},"OperatorRef":{"value":"HSL"},"Monitored":true,"VehicleLocation":{"Longitude":24.82527,"Latitude":60.18218},"Delay":418,"MonitoredCall":{"StopPointRef":"2213208"},"VehicleRef":{"value":"1329"}}},{"ValidUntilTime":1479233251119,"RecordedAtTime":1479233221119,"MonitoredVehicleJourney":{"LineRef":{"value":"4560"},"DirectionRef":{"value":"1"},"FramedVehicleJourneyRef":{"DataFrameRef":{"value":"2016-11-15"},"DatedVehicleJourneyRef":"1928"},"OperatorRef":{"value":"HSL"},"Monitored":true,"VehicleLocation":{"Longitude":24.99434,"Latitude":60.25849},"Delay":104,"MonitoredCall":{"StopPointRef":"1391112"},"VehicleRef":{"value":"1332"}}},{"ValidUntilTime":1479233261513,"RecordedAtTime":1479233231513,"MonitoredVehicleJourney":{"LineRef":{"value":"2550"},"DirectionRef":{"value":"1"},"FramedVehicleJourneyRef":{"DataFrameRef":{"value":"2016-11-15"},"DatedVehicleJourneyRef":"1931"},"OperatorRef":{"value":"HSL"},"Monitored":true,"VehicleLocation":{"Longitude":24.86263,"Latitude":60.22243},"Delay":126,"MonitoredCall":{"StopPointRef":"1465112"},"VehicleRef":{"value":"1341"}}},{"ValidUntilTime":1479233254280,"RecordedAtTime":1479233224280,"MonitoredVehicleJourney":{"LineRef":{"value":"4614"},"DirectionRef":{"value":"2"},"FramedVehicleJourneyRef":{"DataFrameRef":{"value":"2016-11-15"},"DatedVehicleJourneyRef":"2005"},"OperatorRef":{"value":"HSL"},"Monitored":true,"VehicleLocation":{"Longitude":0,"Latitude":0},"Delay":44,"MonitoredCall":{"StopPointRef":"4400234"},"VehicleRef":{"value":"1406"}}},{"ValidUntilTime":1479233258207,"RecordedAtTime":1479233228207,"MonitoredVehicleJourney":{"LineRef":{"value":"4614"},"DirectionRef":{"value":"2"},"FramedVehicleJourneyRef":{"DataFrameRef":{"value":"2016-11-15"},"DatedVehicleJourneyRef":"1935"},"OperatorRef":{"value":"HSL"},"Monitored":true,"VehicleLocation":{"Longitude":24.95861,"Latitude":60.19372},"Delay":122,"MonitoredCall":{"StopPointRef":"1220111"},"VehicleRef":{"value":"1407"}}},{"ValidUntilTime":1479233226714,"RecordedAtTime":1479233196714,"MonitoredVehicleJourney":{"LineRef":{"value":"4615"},"DirectionRef":{"value":"1"},"FramedVehicleJourneyRef":{"DataFrameRef":{"value":"2016-11-15"},"DatedVehicleJourneyRef":"1925"},"OperatorRef":{"value":"HSL"},"Monitored":true,"VehicleLocation":{"Longitude":24.95141,"Latitude":60.30117},"Delay":228,"MonitoredCall":{"StopPointRef":"4520238"},"VehicleRef":{"value":"1408"}}},{"ValidUntilTime":1479233251603,"RecordedAtTime":1479233221603,"MonitoredVehicleJourney":{"LineRef":{"value":"4560"},"DirectionRef":{"value":"1"},"FramedVehicleJourneyRef":{"DataFrameRef":{"value":"2016-11-15"},"DatedVehicleJourneyRef":"2008"},"OperatorRef":{"value":"HSL"},"Monitored":true,"VehicleLocation":{"Longitude":25.12055,"Latitude":60.20562},"Delay":0,"MonitoredCall":{"StopPointRef":"1541193"},"VehicleRef":{"value":"1503"}}},{"ValidUntilTime":1479233274934,"RecordedAtTime":1479233244934,"MonitoredVehicleJourney":{"LineRef":{"value":"4560"},"DirectionRef":{"value":"1"},"FramedVehicleJourneyRef":{"DataFrameRef":{"value":"2016-11-15"},"DatedVehicleJourneyRef":"2018"},"OperatorRef":{"value":"HSL"},"Monitored":true,"VehicleLocation":{"Longitude":25.11964,"Latitude":60.20567},"MonitoredCall":{},"VehicleRef":{"value":"1507"}}},{"ValidUntilTime":1479233225896,"RecordedAtTime":1479233195896,"MonitoredVehicleJourney":{"LineRef":{"value":"4560"},"DirectionRef":{"value":"1"},"FramedVehicleJourneyRef":{"DataFrameRef":{"value":"2016-11-15"},"DatedVehicleJourneyRef":"1938"},"OperatorRef":{"value":"HSL"},"Monitored":true,"VehicleLocation":{"Longitude":25.0513,"Latitude":60.2317},"Delay":64,"MonitoredCall":{"StopPointRef":"1474121"},"VehicleRef":{"value":"1510"}}},{"ValidUntilTime":1479233264776,"RecordedAtTime":1479233234776,"MonitoredVehicleJourney":{"LineRef":{"value":"4560"},"DirectionRef":{"value":"1"},"FramedVehicleJourneyRef":{"DataFrameRef":{"value":"2016-11-15"},"DatedVehicleJourneyRef":"1820"},"OperatorRef":{"value":"HSL"},"Monitored":true,"VehicleLocation":{"Longitude":24.90345,"Latitude":60.20732},"Delay":0,"MonitoredCall":{"StopPointRef":"4150268"},"VehicleRef":{"value":"1511"}}},{"ValidUntilTime":1479233276926,"RecordedAtTime":1479233246926,"MonitoredVehicleJourney":{"LineRef":{"value":"4560"},"DirectionRef":{"value":"2"},"FramedVehicleJourneyRef":{"DataFrameRef":{"value":"2016-11-15"},"DatedVehicleJourneyRef":"2010"},"OperatorRef":{"value":"HSL"},"Monitored":true,"VehicleLocation":{"Longitude":24.84248,"Latitude":60.2583},"Delay":0,"MonitoredCall":{"StopPointRef":"4150269"},"VehicleRef":{"value":"1513"}}},{"ValidUntilTime":1479233279505,"RecordedAtTime":1479233249505,"MonitoredVehicleJourney":{"LineRef":{"value":"4560"},"DirectionRef":{"value":"1"},"FramedVehicleJourneyRef":{"DataFrameRef":{"value":"2016-11-15"},"DatedVehicleJourneyRef":"1908"},"OperatorRef":{"value":"HSL"},"Monitored":true,"VehicleLocation":{"Longitude":24.86134,"Latitude":60.26418},"Delay":208,"MonitoredCall":{"StopPointRef":"4150204"},"VehicleRef":{"value":"1514"}}},{"ValidUntilTime":1479233278931,"RecordedAtTime":1479233248931,"MonitoredVehicleJourney":{"LineRef":{"value":"4560"},"DirectionRef":{"value":"2"},"FramedVehicleJourneyRef":{"DataFrameRef":{"value":"2016-11-15"},"DatedVehicleJourneyRef":"1939"},"OperatorRef":{"value":"HSL"},"Monitored":true,"VehicleLocation":{"Longitude":25.01215,"Latitude":60.24579},"Delay":4,"MonitoredCall":{"StopPointRef":"1382124"},"VehicleRef":{"value":"1515"}}},{"ValidUntilTime":1479233276937,"RecordedAtTime":1479233246937,"MonitoredVehicleJourney":{"LineRef":{"value":"4560"},"DirectionRef":{"value":"2"},"FramedVehicleJourneyRef":{"DataFrameRef":{"value":"2016-11-15"},"DatedVehicleJourneyRef":"1913"},"OperatorRef":{"value":"HSL"},"Monitored":true,"VehicleLocation":{"Longitude":25.14404,"Latitude":60.20362},"Delay":18,"MonitoredCall":{"StopPointRef":"1541169"},"VehicleRef":{"value":"1517"}}},{"ValidUntilTime":1479233252016,"RecordedAtTime":1479233222016,"MonitoredVehicleJourney":{"LineRef":{"value":"4560"},"DirectionRef":{"value":"1"},"FramedVehicleJourneyRef":{"DataFrameRef":{"value":"2016-11-15"},"DatedVehicleJourneyRef":"1948"},"OperatorRef":{"value":"HSL"},"Monitored":true,"VehicleLocation":{"Longitude":25.1193,"Latitude":60.23699},"Delay":0,"MonitoredCall":{"StopPointRef":"1473105"},"VehicleRef":{"value":"1518"}}},{"ValidUntilTime":1479233266158,"RecordedAtTime":1479233236158,"MonitoredVehicleJourney":{"LineRef":{"value":"4560"},"DirectionRef":{"value":"2"},"FramedVehicleJourneyRef":{"DataFrameRef":{"value":"2016-11-15"},"DatedVehicleJourneyRef":"1924"},"OperatorRef":{"value":"HSL"},"Monitored":true,"VehicleLocation":{"Longitude":25.12868,"Latitude":60.23465},"Delay":10,"MonitoredCall":{"StopPointRef":"1473119"},"VehicleRef":{"value":"1519"}}},{"ValidUntilTime":1479233255189,"RecordedAtTime":1479233225189,"MonitoredVehicleJourney":{"LineRef":{"value":"4560"},"DirectionRef":{"value":"1"},"FramedVehicleJourneyRef":{"DataFrameRef":{"value":"2016-11-15"},"DatedVehicleJourneyRef":"1958"},"OperatorRef":{"value":"HSL"},"Monitored":true,"VehicleLocation":{"Longitude":25.14413,"Latitude":60.20764},"Delay":0,"MonitoredCall":{"StopPointRef":"1531115"},"VehicleRef":{"value":"1520"}}},{"ValidUntilTime":1479233258224,"RecordedAtTime":1479233228224,"MonitoredVehicleJourney":{"LineRef":{"value":"1075"},"DirectionRef":{"value":"2"},"FramedVehicleJourneyRef":{"DataFrameRef":{"value":"2016-11-15"},"DatedVehicleJourneyRef":"1942"},"OperatorRef":{"value":"HSL"},"Monitored":true,"VehicleLocation":{"Longitude":24.91174,"Latitude":60.58185},"MonitoredCall":{},"VehicleRef":{"value":"1526"}}},{"ValidUntilTime":1479233257580,"RecordedAtTime":1479233227580,"MonitoredVehicleJourney":{"LineRef":{"value":"1023"},"DirectionRef":{"value":"1"},"FramedVehicleJourneyRef":{"DataFrameRef":{"value":"2016-11-15"},"DatedVehicleJourneyRef":"2007"},"OperatorRef":{"value":"HSL"},"Monitored":true,"VehicleLocation":{"Longitude":24.94279,"Latitude":60.17109},"Delay":0,"MonitoredCall":{"StopPointRef":"1020116"},"VehicleRef":{"value":"1601"}}},{"ValidUntilTime":1479233271935,"RecordedAtTime":1479233241935,"MonitoredVehicleJourney":{"LineRef":{"value":"1023"},"DirectionRef":{"value":"1"},"FramedVehicleJourneyRef":{"DataFrameRef":{"value":"2016-11-15"},"DatedVehicleJourneyRef":"1913"},"OperatorRef":{"value":"HSL"},"Monitored":true,"VehicleLocation":{"Longitude":24.9055,"Latitude":60.20677},"Delay":0,"MonitoredCall":{"StopPointRef":"1160113"},"VehicleRef":{"value":"1602"}}},{"ValidUntilTime":1479233262903,"RecordedAtTime":1479233232903,"MonitoredVehicleJourney":{"LineRef":{"value":"1023"},"DirectionRef":{"value":"2"},"FramedVehicleJourneyRef":{"DataFrameRef":{"value":"2016-11-15"},"DatedVehicleJourneyRef":"1949"},"OperatorRef":{"value":"HSL"},"Monitored":true,"VehicleLocation":{"Longitude":0,"Latitude":0},"Delay":124,"MonitoredCall":{"StopPointRef":"1122135"},"VehicleRef":{"value":"1603"}}},{"ValidUntilTime":1479233271745,"RecordedAtTime":1479233241745,"MonitoredVehicleJourney":{"LineRef":{"value":"1023"},"DirectionRef":{"value":"2"},"FramedVehicleJourneyRef":{"DataFrameRef":{"value":"2016-11-15"},"DatedVehicleJourneyRef":"1916"},"OperatorRef":{"value":"HSL"},"Monitored":true,"VehicleLocation":{"Longitude":24.90294,"Latitude":60.20714},"Delay":94,"MonitoredCall":{"StopPointRef":"1020201"},"VehicleRef":{"value":"1604"}}},{"ValidUntilTime":1479233265168,"RecordedAtTime":1479233235168,"MonitoredVehicleJourney":{"LineRef":{"value":"1023"},"DirectionRef":{"value":"2"},"FramedVehicleJourneyRef":{"DataFrameRef":{"value":"2016-11-15"},"DatedVehicleJourneyRef":"2009"},"OperatorRef":{"value":"HSL"},"Monitored":true,"VehicleLocation":{"Longitude":24.90807,"Latitude":60.20295},"Delay":0,"MonitoredCall":{"StopPointRef":"1160113"},"VehicleRef":{"value":"1605"}}},{"ValidUntilTime":1479233259017,"RecordedAtTime":1479233229017,"MonitoredVehicleJourney":{"LineRef":{"value":"1023"},"DirectionRef":{"value":"1"},"FramedVehicleJourneyRef":{"DataFrameRef":{"value":"2016-11-15"},"DatedVehicleJourneyRef":"1813"},"OperatorRef":{"value":"HSL"},"Monitored":true,"VehicleLocation":{"Longitude":24.9361,"Latitude":60.19746},"Delay":3094,"MonitoredCall":{"StopPointRef":"1292122"},"VehicleRef":{"value":"1606"}}},{"ValidUntilTime":1479233267139,"RecordedAtTime":1479233237139,"MonitoredVehicleJourney":{"LineRef":{"value":"1058"},"DirectionRef":{"value":"1"},"FramedVehicleJourneyRef":{"DataFrameRef":{"value":"2016-11-15"},"DatedVehicleJourneyRef":"2010"},"OperatorRef":{"value":"HSL"},"Monitored":true,"VehicleLocation":{"Longitude":25.07761,"Latitude":60.21045},"MonitoredCall":{},"VehicleRef":{"value":"3253"}}},{"ValidUntilTime":1479233268140,"RecordedAtTime":1479233238140,"MonitoredVehicleJourney":{"LineRef":{"value":"1058"},"DirectionRef":{"value":"1"},"FramedVehicleJourneyRef":{"DataFrameRef":{"value":"2016-11-15"},"DatedVehicleJourneyRef":"1854"},"OperatorRef":{"value":"HSL"},"Monitored":true,"VehicleLocation":{"Longitude":24.91715,"Latitude":60.21076},"Delay":928,"MonitoredCall":{"StopPointRef":"1304161"},"VehicleRef":{"value":"3614"}}},{"ValidUntilTime":1479233273526,"RecordedAtTime":1479233243526,"MonitoredVehicleJourney":{"LineRef":{"value":"1058"},"DirectionRef":{"value":"2"},"FramedVehicleJourneyRef":{"DataFrameRef":{"value":"2016-11-15"},"DatedVehicleJourneyRef":"1944"},"OperatorRef":{"value":"HSL"},"Monitored":true,"VehicleLocation":{"Longitude":24.94083,"Latitude":60.19418},"Delay":190,"MonitoredCall":{"StopPointRef":"1122126"},"VehicleRef":{"value":"3615"}}},{"ValidUntilTime":1479233231189,"RecordedAtTime":1479233201189,"MonitoredVehicleJourney":{"LineRef":{"value":"1059"},"DirectionRef":{"value":"1"},"FramedVehicleJourneyRef":{"DataFrameRef":{"value":"2016-11-15"},"DatedVehicleJourneyRef":"1940"},"OperatorRef":{"value":"HSL"},"Monitored":true,"VehicleLocation":{"Longitude":24.88925,"Latitude":60.2095},"Delay":158,"MonitoredCall":{"StopPointRef":"1291220"},"VehicleRef":{"value":"3618"}}},{"ValidUntilTime":1479233267645,"RecordedAtTime":1479233237645,"MonitoredVehicleJourney":{"LineRef":{"value":"1051"},"DirectionRef":{"value":"2"},"FramedVehicleJourneyRef":{"DataFrameRef":{"value":"2016-11-15"},"DatedVehicleJourneyRef":"1958"},"OperatorRef":{"value":"HSL"},"Monitored":true,"VehicleLocation":{"Longitude":0,"Latitude":0},"Delay":338,"MonitoredCall":{"StopPointRef":"1320111"},"VehicleRef":{"value":"3622"}}},{"ValidUntilTime":1479233260612,"RecordedAtTime":1479233230612,"MonitoredVehicleJourney":{"LineRef":{"value":"1051"},"DirectionRef":{"value":"1"},"FramedVehicleJourneyRef":{"DataFrameRef":{"value":"2016-11-15"},"DatedVehicleJourneyRef":"1942"},"OperatorRef":{"value":"HSL"},"Monitored":true,"VehicleLocation":{"Longitude":24.93369,"Latitude":60.22211},"Delay":246,"MonitoredCall":{"StopPointRef":"1286134"},"VehicleRef":{"value":"3624"}}},{"ValidUntilTime":1479233256658,"RecordedAtTime":1479233226658,"MonitoredVehicleJourney":{"LineRef":{"value":"1051"},"DirectionRef":{"value":"1"},"FramedVehicleJourneyRef":{"DataFrameRef":{"value":"2016-11-15"},"DatedVehicleJourneyRef":"2004"},"OperatorRef":{"value":"HSL"},"Monitored":true,"VehicleLocation":{"Longitude":24.95039,"Latitude":60.18148},"Delay":50,"MonitoredCall":{"StopPointRef":"1113123"},"VehicleRef":{"value":"3625"}}},{"ValidUntilTime":1479233274064,"RecordedAtTime":1479233244064,"MonitoredVehicleJourney":{"LineRef":{"value":"1051"},"DirectionRef":{"value":"1"},"FramedVehicleJourneyRef":{"DataFrameRef":{"value":"2016-11-15"},"DatedVehicleJourneyRef":"1922"},"OperatorRef":{"value":"HSL"},"Monitored":true,"VehicleLocation":{"Longitude":24.84671,"Latitude":60.23174},"Delay":210,"MonitoredCall":{"StopPointRef":"1320101"},"VehicleRef":{"value":"3630"}}},{"ValidUntilTime":1479233263835,"RecordedAtTime":1479233233835,"MonitoredVehicleJourney":{"LineRef":{"value":"1057"},"DirectionRef":{"value":"2"},"FramedVehicleJourneyRef":{"DataFrameRef":{"value":"2016-11-15"},"DatedVehicleJourneyRef":"2018"},"OperatorRef":{"value":"HSL"},"Monitored":true,"VehicleLocation":{"Longitude":25.08135,"Latitude":60.23665},"MonitoredCall":{},"VehicleRef":{"value":"3631"}}},{"ValidUntilTime":1479233254703,"RecordedAtTime":1479233224703,"MonitoredVehicleJourney":{"LineRef":{"value":"1052"},"DirectionRef":{"value":"1"},"FramedVehicleJourneyRef":{"DataFrameRef":{"value":"2016-11-15"},"DatedVehicleJourneyRef":"2017"},"OperatorRef":{"value":"HSL"},"Monitored":true,"VehicleLocation":{"Longitude":24.88536,"Latitude":60.19578},"MonitoredCall":{},"VehicleRef":{"value":"3637"}}},{"ValidUntilTime":1479233256189,"RecordedAtTime":1479233226189,"MonitoredVehicleJourney":{"LineRef":{"value":"1052"},"DirectionRef":{"value":"1"},"FramedVehicleJourneyRef":{"DataFrameRef":{"value":"2016-11-15"},"DatedVehicleJourneyRef":"1932"},"OperatorRef":{"value":"HSL"},"Monitored":true,"VehicleLocation":{"Longitude":24.96577,"Latitude":60.22325},"Delay":0,"MonitoredCall":{"StopPointRef":"1260113"},"VehicleRef":{"value":"3638"}}},{"ValidUntilTime":1479233260609,"RecordedAtTime":1479233230609,"MonitoredVehicleJourney":{"LineRef":{"value":"1052"},"DirectionRef":{"value":"2"},"FramedVehicleJourneyRef":{"DataFrameRef":{"value":"2016-11-15"},"DatedVehicleJourneyRef":"2013"},"OperatorRef":{"value":"HSL"},"Monitored":true,"VehicleLocation":{"Longitude":24.97948,"Latitude":60.20961},"MonitoredCall":{},"VehicleRef":{"value":"3641"}}},{"ValidUntilTime":1479233256193,"RecordedAtTime":1479233226193,"MonitoredVehicleJourney":{"LineRef":{"value":"1052"},"DirectionRef":{"value":"2"},"FramedVehicleJourneyRef":{"DataFrameRef":{"value":"2016-11-15"},"DatedVehicleJourneyRef":"1943"},"OperatorRef":{"value":"HSL"},"Monitored":true,"VehicleLocation":{"Longitude":24.91622,"Latitude":60.2299},"Delay":52,"MonitoredCall":{"StopPointRef":"1281115"},"VehicleRef":{"value":"3643"}}},{"ValidUntilTime":1479233261004,"RecordedAtTime":1479233231004,"MonitoredVehicleJourney":{"LineRef":{"value":"1072"},"DirectionRef":{"value":"1"},"FramedVehicleJourneyRef":{"DataFrameRef":{"value":"2016-11-15"},"DatedVehicleJourneyRef":"2017"},"OperatorRef":{"value":"HSL"},"Monitored":true,"VehicleLocation":{"Longitude":24.94406,"Latitude":60.1719},"MonitoredCall":{},"VehicleRef":{"value":"3648"}}},{"ValidUntilTime":1479233268125,"RecordedAtTime":1479233238125,"MonitoredVehicleJourney":{"LineRef":{"value":"1072"},"DirectionRef":{"value":"2"},"FramedVehicleJourneyRef":{"DataFrameRef":{"value":"2016-11-15"},"DatedVehicleJourneyRef":"1947"},"OperatorRef":{"value":"HSL"},"Monitored":true,"VehicleLocation":{"Longitude":24.95057,"Latitude":60.23064},"Delay":0,"MonitoredCall":{"StopPointRef":"1284127"},"VehicleRef":{"value":"3654"}}},{"ValidUntilTime":1479233270821,"RecordedAtTime":1479233240821,"MonitoredVehicleJourney":{"LineRef":{"value":"1072"},"DirectionRef":{"value":"1"},"FramedVehicleJourneyRef":{"DataFrameRef":{"value":"2016-11-15"},"DatedVehicleJourneyRef":"1903"},"OperatorRef":{"value":"HSL"},"Monitored":true,"VehicleLocation":{"Longitude":24.93144,"Latitude":60.21036},"Delay":0,"MonitoredCall":{"StopPointRef":"1392154"},"VehicleRef":{"value":"3656"}}},{"ValidUntilTime":1479233255763,"RecordedAtTime":1479233225763,"MonitoredVehicleJourney":{"LineRef":{"value":"1072"},"DirectionRef":{"value":"1"},"FramedVehicleJourneyRef":{"DataFrameRef":{"value":"2016-11-15"},"DatedVehicleJourneyRef":"1957"},"OperatorRef":{"value":"HSL"},"Monitored":true,"VehicleLocation":{"Longitude":24.9634,"Latitude":60.19036},"Delay":42,"MonitoredCall":{"StopPointRef":"1220184"},"VehicleRef":{"value":"3657"}}},{"ValidUntilTime":1479233265171,"RecordedAtTime":1479233235171,"MonitoredVehicleJourney":{"LineRef":{"value":"1072"},"DirectionRef":{"value":"2"},"FramedVehicleJourneyRef":{"DataFrameRef":{"value":"2016-11-15"},"DatedVehicleJourneyRef":"2007"},"OperatorRef":{"value":"HSL"},"Monitored":true,"VehicleLocation":{"Longitude":25.01609,"Latitude":60.26576},"Delay":2,"MonitoredCall":{"StopPointRef":"1392154"},"VehicleRef":{"value":"3659"}}},{"ValidUntilTime":1479233240484,"RecordedAtTime":1479233210484,"MonitoredVehicleJourney":{"LineRef":{"value":"1072"},"DirectionRef":{"value":"1"},"FramedVehicleJourneyRef":{"DataFrameRef":{"value":"2016-11-15"},"DatedVehicleJourneyRef":"1937"},"OperatorRef":{"value":"HSL"},"Monitored":true,"VehicleLocation":{"Longitude":24.97691,"Latitude":60.23843},"Delay":92,"MonitoredCall":{"StopPointRef":"1370103"},"VehicleRef":{"value":"3661"}}},{"ValidUntilTime":1479233261923,"RecordedAtTime":1479233231923,"MonitoredVehicleJourney":{"LineRef":{"value":"1057"},"DirectionRef":{"value":"1"},"FramedVehicleJourneyRef":{"DataFrameRef":{"value":"2016-11-15"},"DatedVehicleJourneyRef":"1940"},"OperatorRef":{"value":"HSL"},"Monitored":true,"VehicleLocation":{"Longitude":25.01235,"Latitude":60.2271},"Delay":0,"MonitoredCall":{"StopPointRef":"1362139"},"VehicleRef":{"value":"3663"}}},{"ValidUntilTime":1479233277742,"RecordedAtTime":1479233247742,"MonitoredVehicleJourney":{"LineRef":{"value":"1057"},"DirectionRef":{"value":"1"},"FramedVehicleJourneyRef":{"DataFrameRef":{"value":"2016-11-15"},"DatedVehicleJourneyRef":"2020"},"OperatorRef":{"value":"HSL"},"Monitored":true,"VehicleLocation":{"Longitude":24.88552,"Latitude":60.19591},"MonitoredCall":{},"VehicleRef":{"value":"3664"}}},{"ValidUntilTime":1479233256688,"RecordedAtTime":1479233226688,"MonitoredVehicleJourney":{"LineRef":{"value":"1057"},"DirectionRef":{"value":"2"},"FramedVehicleJourneyRef":{"DataFrameRef":{"value":"2016-11-15"},"DatedVehicleJourneyRef":"1938"},"OperatorRef":{"value":"HSL"},"Monitored":true,"VehicleLocation":{"Longitude":24.94882,"Latitude":60.20978},"Delay":296,"MonitoredCall":{"StopPointRef":"1250112"},"VehicleRef":{"value":"3665"}}},{"ValidUntilTime":1479233263833,"RecordedAtTime":1479233233833,"MonitoredVehicleJourney":{"LineRef":{"value":"1057"},"DirectionRef":{"value":"2"},"FramedVehicleJourneyRef":{"DataFrameRef":{"value":"2016-11-15"},"DatedVehicleJourneyRef":"1958"},"OperatorRef":{"value":"HSL"},"Monitored":true,"VehicleLocation":{"Longitude":25.05165,"Latitude":60.23066},"Delay":106,"MonitoredCall":{"StopPointRef":"1362102"},"VehicleRef":{"value":"3667"}}},{"ValidUntilTime":1479233266646,"RecordedAtTime":1479233236646,"MonitoredVehicleJourney":{"LineRef":{"value":"1057"},"DirectionRef":{"value":"1"},"FramedVehicleJourneyRef":{"DataFrameRef":{"value":"2016-11-15"},"DatedVehicleJourneyRef":"2000"},"OperatorRef":{"value":"HSL"},"Monitored":true,"VehicleLocation":{"Longitude":24.8769,"Latitude":60.20081},"Delay":196,"MonitoredCall":{"StopPointRef":"1301146"},"VehicleRef":{"value":"3668"}}},{"ValidUntilTime":1479233263846,"RecordedAtTime":1479233233846,"MonitoredVehicleJourney":{"LineRef":{"value":"1051"},"DirectionRef":{"value":"2"},"FramedVehicleJourneyRef":{"DataFrameRef":{"value":"2016-11-15"},"DatedVehicleJourneyRef":"1938"},"OperatorRef":{"value":"HSL"},"Monitored":true,"VehicleLocation":{"Longitude":0,"Latitude":0},"Delay":100,"MonitoredCall":{"StopPointRef":"1286135"},"VehicleRef":{"value":"3670"}}},{"ValidUntilTime":1479233278952,"RecordedAtTime":1479233248952,"MonitoredVehicleJourney":{"LineRef":{"value":"1051"},"DirectionRef":{"value":"1"},"FramedVehicleJourneyRef":{"DataFrameRef":{"value":"2016-11-15"},"DatedVehicleJourneyRef":"2024"},"OperatorRef":{"value":"HSL"},"Monitored":true,"VehicleLocation":{"Longitude":24.95211,"Latitude":60.17935},"MonitoredCall":{},"VehicleRef":{"value":"3671"}}},{"ValidUntilTime":1479233273925,"RecordedAtTime":1479233243925,"MonitoredVehicleJourney":{"LineRef":{"value":"2552"},"DirectionRef":{"value":"1"},"FramedVehicleJourneyRef":{"DataFrameRef":{"value":"2016-11-15"},"DatedVehicleJourneyRef":"1941"},"OperatorRef":{"value":"HSL"},"Monitored":true,"VehicleLocation":{"Longitude":24.88146,"Latitude":60.20283},"Delay":26,"MonitoredCall":{"StopPointRef":"1301158"},"VehicleRef":{"value":"3674"}}},{"ValidUntilTime":1479233259834,"RecordedAtTime":1479233229834,"MonitoredVehicleJourney":{"LineRef":{"value":"1051"},"DirectionRef":{"value":"1"},"FramedVehicleJourneyRef":{"DataFrameRef":{"value":"2016-11-15"},"DatedVehicleJourneyRef":"1844"},"OperatorRef":{"value":"HSL"},"Monitored":true,"VehicleLocation":{"Longitude":24.93195,"Latitude":60.21122},"Delay":90,"MonitoredCall":{"StopPointRef":"1333182"},"VehicleRef":{"value":"3705"}}},{"ValidUntilTime":1479233276605,"RecordedAtTime":1479233246605,"MonitoredVehicleJourney":{"LineRef":{"value":"2552"},"DirectionRef":{},"FramedVehicleJourneyRef":{"DataFrameRef":{"value":"2016-11-15"}},"OperatorRef":{"value":"HSL"},"Monitored":true,"VehicleLocation":{"Longitude":24.88741,"Latitude":60.55428},"MonitoredCall":{},"VehicleRef":{"value":"3753"}}},{"ValidUntilTime":1479233260215,"RecordedAtTime":1479233230215,"MonitoredVehicleJourney":{"LineRef":{"value":"1050"},"DirectionRef":{"value":"2"},"FramedVehicleJourneyRef":{"DataFrameRef":{"value":"2016-11-15"},"DatedVehicleJourneyRef":"2007"},"OperatorRef":{"value":"HSL"},"Monitored":true,"VehicleLocation":{"Longitude":24.93423,"Latitude":60.23442},"Delay":0,"MonitoredCall":{"StopPointRef":"1282149"},"VehicleRef":{"value":"3810"}}},{"ValidUntilTime":1479233277401,"RecordedAtTime":1479233247401,"MonitoredVehicleJourney":{"LineRef":{"value":"1073"},"DirectionRef":{"value":"2"},"FramedVehicleJourneyRef":{"DataFrameRef":{"value":"2016-11-15"},"DatedVehicleJourneyRef":"1943"},"OperatorRef":{"value":"HSL"},"Monitored":true,"VehicleLocation":{"Longitude":25.01036,"Latitude":60.22968},"Delay":0,"MonitoredCall":{"StopPointRef":"1363101"},"VehicleRef":{"value":"4003"}}},{"ValidUntilTime":1479233274451,"RecordedAtTime":1479233244451,"MonitoredVehicleJourney":{"LineRef":{"value":"1073"},"DirectionRef":{"value":"1"},"FramedVehicleJourneyRef":{"DataFrameRef":{"value":"2016-11-15"},"DatedVehicleJourneyRef":"1952"},"OperatorRef":{"value":"HSL"},"Monitored":true,"VehicleLocation":{"Longitude":24.98644,"Latitude":60.22244},"Delay":116,"MonitoredCall":{"StopPointRef":"1362105"},"VehicleRef":{"value":"4012"}}},{"ValidUntilTime":1479233251611,"RecordedAtTime":1479233221611,"MonitoredVehicleJourney":{"LineRef":{"value":"1016"},"DirectionRef":{"value":"2"},"FramedVehicleJourneyRef":{"DataFrameRef":{"value":"2016-11-15"},"DatedVehicleJourneyRef":"2010"},"OperatorRef":{"value":"HSL"},"Monitored":true,"VehicleLocation":{"Longitude":24.98313,"Latitude":60.18005},"MonitoredCall":{},"VehicleRef":{"value":"4025"}}},{"ValidUntilTime":1479233272766,"RecordedAtTime":1479233242766,"MonitoredVehicleJourney":{"LineRef":{"value":"1016"},"DirectionRef":{"value":"2"},"FramedVehicleJourneyRef":{"DataFrameRef":{"value":"2016-11-15"},"DatedVehicleJourneyRef":"1950"},"OperatorRef":{"value":"HSL"},"Monitored":true,"VehicleLocation":{"Longitude":24.96023,"Latitude":60.17615},"Delay":0,"MonitoredCall":{"StopPointRef":"1010110"},"VehicleRef":{"value":"4026"}}},{"ValidUntilTime":1479233263365,"RecordedAtTime":1479233233365,"MonitoredVehicleJourney":{"LineRef":{"value":"1054"},"DirectionRef":{"value":"2"},"FramedVehicleJourneyRef":{"DataFrameRef":{"value":"2016-11-15"},"DatedVehicleJourneyRef":"1959"},"OperatorRef":{"value":"HSL"},"Monitored":true,"VehicleLocation":{"Longitude":25.07331,"Latitude":60.22788},"Delay":256,"MonitoredCall":{"StopPointRef":"1454113"},"VehicleRef":{"value":"4034"}}},{"ValidUntilTime":1479233234246,"RecordedAtTime":1479233204246,"MonitoredVehicleJourney":{"LineRef":{"value":"1054"},"DirectionRef":{"value":"2"},"FramedVehicleJourneyRef":{"DataFrameRef":{"value":"2016-11-15"},"DatedVehicleJourneyRef":"1844"},"OperatorRef":{"value":"HSL"},"Monitored":true,"VehicleLocation":{"Longitude":24.9973,"Latitude":60.28845},"Delay":318,"MonitoredCall":{"StopPointRef":"1465106"},"VehicleRef":{"value":"4035"}}},{"ValidUntilTime":1479233270316,"RecordedAtTime":1479233240316,"MonitoredVehicleJourney":{"LineRef":{"value":"1054"},"DirectionRef":{"value":"2"},"FramedVehicleJourneyRef":{"DataFrameRef":{"value":"2016-11-15"},"DatedVehicleJourneyRef":"1959"},"OperatorRef":{"value":"HSL"},"Monitored":true,"VehicleLocation":{"Longitude":25.05995,"Latitude":60.2597},"MonitoredCall":{},"VehicleRef":{"value":"4038"}}},{"ValidUntilTime":1479233267127,"RecordedAtTime":1479233237127,"MonitoredVehicleJourney":{"LineRef":{"value":"1054"},"DirectionRef":{"value":"2"},"FramedVehicleJourneyRef":{"DataFrameRef":{"value":"2016-11-15"},"DatedVehicleJourneyRef":"1944"},"OperatorRef":{"value":"HSL"},"Monitored":true,"VehicleLocation":{"Longitude":24.88735,"Latitude":60.23523},"Delay":180,"MonitoredCall":{"StopPointRef":"1294242"},"VehicleRef":{"value":"4041"}}},{"ValidUntilTime":1479233261531,"RecordedAtTime":1479233231531,"MonitoredVehicleJourney":{"LineRef":{"value":"1054"},"DirectionRef":{"value":"1"},"FramedVehicleJourneyRef":{"DataFrameRef":{"value":"2016-11-15"},"DatedVehicleJourneyRef":"1953"},"OperatorRef":{"value":"HSL"},"Monitored":true,"VehicleLocation":{"Longitude":24.9285,"Latitude":60.24107},"Delay":4,"MonitoredCall":{"StopPointRef":"1341108"},"VehicleRef":{"value":"4043"}}},{"ValidUntilTime":1479233275668,"RecordedAtTime":1479233245668,"MonitoredVehicleJourney":{"LineRef":{"value":"1506"},"DirectionRef":{"value":"1"},"FramedVehicleJourneyRef":{"DataFrameRef":{"value":"2016-11-15"},"DatedVehicleJourneyRef":"2015"},"OperatorRef":{"value":"HSL"},"Monitored":true,"VehicleLocation":{"Longitude":24.91059,"Latitude":60.18953},"MonitoredCall":{},"VehicleRef":{"value":"5568"}}},{"ValidUntilTime":1479233257558,"RecordedAtTime":1479233227558,"MonitoredVehicleJourney":{"LineRef":{"value":"1043"},"DirectionRef":{"value":"1"},"FramedVehicleJourneyRef":{"DataFrameRef":{"value":"2016-11-15"},"DatedVehicleJourneyRef":"1937"},"OperatorRef":{"value":"HSL"},"Monitored":true,"VehicleLocation":{"Longitude":24.87376,"Latitude":60.23997},"Delay":58,"MonitoredCall":{"StopPointRef":"1331165"},"VehicleRef":{"value":"8603"}}},{"ValidUntilTime":1479233252415,"RecordedAtTime":1479233222415,"MonitoredVehicleJourney":{"LineRef":{"value":"4614"},"DirectionRef":{"value":"1"},"FramedVehicleJourneyRef":{"DataFrameRef":{"value":"2016-11-15"},"DatedVehicleJourneyRef":"1750"},"OperatorRef":{"value":"HSL"},"Monitored":true,"VehicleLocation":{"Longitude":24.90427,"Latitude":60.20748},"Delay":3094,"MonitoredCall":{"StopPointRef":"4400222"},"VehicleRef":{"value":"8619"}}},{"ValidUntilTime":1479233269432,"RecordedAtTime":1479233239432,"MonitoredVehicleJourney":{"LineRef":{"value":"1077"},"DirectionRef":{"value":"1"},"FramedVehicleJourneyRef":{"DataFrameRef":{"value":"2016-11-15"},"DatedVehicleJourneyRef":"1945"},"OperatorRef":{"value":"HSL"},"Monitored":true,"VehicleLocation":{"Longitude":25.06657,"Latitude":60.25136},"Delay":0,"MonitoredCall":{"StopPointRef":"1414144"},"VehicleRef":{"value":"8704"}}},{"ValidUntilTime":1479233259005,"RecordedAtTime":1479233229005,"MonitoredVehicleJourney":{"LineRef":{"value":"1037"},"DirectionRef":{"value":"1"},"FramedVehicleJourneyRef":{"DataFrameRef":{"value":"2016-11-15"},"DatedVehicleJourneyRef":"1956"},"OperatorRef":{"value":"HSL"},"Monitored":true,"VehicleLocation":{"Longitude":24.91094,"Latitude":60.19066},"Delay":56,"MonitoredCall":{"StopPointRef":"1150101"},"VehicleRef":{"value":"8804"}}},{"ValidUntilTime":1479233259826,"RecordedAtTime":1479233229826,"MonitoredVehicleJourney":{"LineRef":{"value":"1037"},"DirectionRef":{"value":"2"},"FramedVehicleJourneyRef":{"DataFrameRef":{"value":"2016-11-15"},"DatedVehicleJourneyRef":"1959"},"OperatorRef":{"value":"HSL"},"Monitored":true,"VehicleLocation":{"Longitude":24.86277,"Latitude":60.24292},"Delay":116,"MonitoredCall":{"StopPointRef":"1333151"},"VehicleRef":{"value":"8805"}}},{"ValidUntilTime":1479233275327,"RecordedAtTime":1479233245327,"MonitoredVehicleJourney":{"LineRef":{"value":"1037"},"DirectionRef":{"value":"1"},"FramedVehicleJourneyRef":{"DataFrameRef":{"value":"2016-11-15"},"DatedVehicleJourneyRef":"1936"},"OperatorRef":{"value":"HSL"},"Monitored":true,"VehicleLocation":{"Longitude":24.85184,"Latitude":60.24451},"Delay":258,"MonitoredCall":{"StopPointRef":"1333148"},"VehicleRef":{"value":"8808"}}},{"ValidUntilTime":1479233252388,"RecordedAtTime":1479233222388,"MonitoredVehicleJourney":{"LineRef":{"value":"1014"},"DirectionRef":{"value":"2"},"FramedVehicleJourneyRef":{"DataFrameRef":{"value":"2016-11-15"},"DatedVehicleJourneyRef":"1933"},"OperatorRef":{"value":"HSL"},"Monitored":true,"VehicleLocation":{"Longitude":24.9341,"Latitude":60.16365},"Delay":296,"MonitoredCall":{"StopPointRef":"1040124"},"VehicleRef":{"value":"8810"}}},{"ValidUntilTime":1479233261924,"RecordedAtTime":1479233231924,"MonitoredVehicleJourney":{"LineRef":{"value":"1037"},"DirectionRef":{"value":"1"},"FramedVehicleJourneyRef":{"DataFrameRef":{"value":"2016-11-15"},"DatedVehicleJourneyRef":"2016"},"OperatorRef":{"value":"HSL"},"Monitored":true,"VehicleLocation":{"Longitude":24.9298,"Latitude":60.16843},"MonitoredCall":{},"VehicleRef":{"value":"8814"}}},{"ValidUntilTime":1479233268442,"RecordedAtTime":1479233238442,"MonitoredVehicleJourney":{"LineRef":{"value":"1043"},"DirectionRef":{"value":"2"},"FramedVehicleJourneyRef":{"DataFrameRef":{"value":"2016-11-15"},"DatedVehicleJourneyRef":"1933"},"OperatorRef":{"value":"HSL"},"Monitored":true,"VehicleLocation":{"Longitude":24.9385,"Latitude":60.1741},"Delay":0,"MonitoredCall":{"StopPointRef":"1020128"},"VehicleRef":{"value":"8901"}}},{"ValidUntilTime":1479233245869,"RecordedAtTime":1479233215869,"MonitoredVehicleJourney":{"LineRef":{"value":"1043"},"DirectionRef":{"value":"2"},"FramedVehicleJourneyRef":{"DataFrameRef":{"value":"2016-11-15"},"DatedVehicleJourneyRef":"1953"},"OperatorRef":{"value":"HSL"},"Monitored":true,"VehicleLocation":{"Longitude":24.89006,"Latitude":60.2321},"Delay":0,"MonitoredCall":{"StopPointRef":"1293135"},"VehicleRef":{"value":"8902"}}},{"ValidUntilTime":1479233232979,"RecordedAtTime":1479233202979,"MonitoredVehicleJourney":{"LineRef":{"value":"1043"},"DirectionRef":{"value":"1"},"FramedVehicleJourneyRef":{"DataFrameRef":{"value":"2016-11-15"},"DatedVehicleJourneyRef":"1957"},"OperatorRef":{"value":"HSL"},"Monitored":true,"VehicleLocation":{"Longitude":24.91642,"Latitude":60.18963},"Delay":90,"MonitoredCall":{"StopPointRef":"1180214"},"VehicleRef":{"value":"8903"}}},{"ValidUntilTime":1479233230107,"RecordedAtTime":1479233200107,"MonitoredVehicleJourney":{"LineRef":{"value":"1043"},"DirectionRef":{"value":"2"},"FramedVehicleJourneyRef":{"DataFrameRef":{"value":"2016-11-15"},"DatedVehicleJourneyRef":"2013"},"OperatorRef":{"value":"HSL"},"Monitored":true,"VehicleLocation":{"Longitude":24.89755,"Latitude":60.25632},"MonitoredCall":{},"VehicleRef":{"value":"8904"}}},{"ValidUntilTime":1479233230105,"RecordedAtTime":1479233200105,"MonitoredVehicleJourney":{"LineRef":{"value":"4611"},"DirectionRef":{"value":"1"},"FramedVehicleJourneyRef":{"DataFrameRef":{"value":"2016-11-15"},"DatedVehicleJourneyRef":"1930"},"OperatorRef":{"value":"HSL"},"Monitored":true,"VehicleLocation":{"Longitude":24.99768,"Latitude":60.28787},"Delay":0,"MonitoredCall":{"StopPointRef":"4680238"},"VehicleRef":{"value":"8906"}}},{"ValidUntilTime":1479233259031,"RecordedAtTime":1479233229031,"MonitoredVehicleJourney":{"LineRef":{"value":"1018"},"DirectionRef":{"value":"1"},"FramedVehicleJourneyRef":{"DataFrameRef":{"value":"2016-11-15"},"DatedVehicleJourneyRef":"2005"},"OperatorRef":{"value":"HSL"},"Monitored":true,"VehicleLocation":{"Longitude":24.94135,"Latitude":60.15759},"Delay":60,"MonitoredCall":{"StopPointRef":"1060102"},"VehicleRef":{"value":"8909"}}},{"ValidUntilTime":1479233273550,"RecordedAtTime":1479233243550,"MonitoredVehicleJourney":{"LineRef":{"value":"1075"},"DirectionRef":{"value":"1"},"FramedVehicleJourneyRef":{"DataFrameRef":{"value":"2016-11-15"},"DatedVehicleJourneyRef":"1837"},"OperatorRef":{"value":"HSL"},"Monitored":true,"VehicleLocation":{"Longitude":25.06239,"Latitude":60.21271},"Delay":0,"MonitoredCall":{"StopPointRef":"1402125"},"VehicleRef":{"value":"8914"}}},{"ValidUntilTime":1479233261014,"RecordedAtTime":1479233231014,"MonitoredVehicleJourney":{"LineRef":{"value":"1018"},"DirectionRef":{"value":"1"},"FramedVehicleJourneyRef":{"DataFrameRef":{"value":"2016-11-15"},"DatedVehicleJourneyRef":"2025"},"OperatorRef":{"value":"HSL"},"Monitored":true,"VehicleLocation":{"Longitude":24.94276,"Latitude":60.15497},"MonitoredCall":{},"VehicleRef":{"value":"8917"}}},{"ValidUntilTime":1479233255223,"RecordedAtTime":1479233225223,"MonitoredVehicleJourney":{"LineRef":{"value":"1014"},"DirectionRef":{"value":"2"},"FramedVehicleJourneyRef":{"DataFrameRef":{"value":"2016-11-15"},"DatedVehicleJourneyRef":"1809"},"OperatorRef":{"value":"HSL"},"Monitored":true,"VehicleLocation":{"Longitude":24.88523,"Latitude":60.19618},"Delay":3094,"MonitoredCall":{"StopPointRef":"1301124"},"VehicleRef":{"value":"8921"}}},{"ValidUntilTime":1479233271942,"RecordedAtTime":1479233241942,"MonitoredVehicleJourney":{"LineRef":{"value":"1014"},"DirectionRef":{"value":"1"},"FramedVehicleJourneyRef":{"DataFrameRef":{"value":"2016-11-15"},"DatedVehicleJourneyRef":"1926"},"OperatorRef":{"value":"HSL"},"Monitored":true,"VehicleLocation":{"Longitude":24.88148,"Latitude":60.21136},"Delay":418,"MonitoredCall":{"StopPointRef":"1465177"},"VehicleRef":{"value":"8922"}}},{"ValidUntilTime":1479233240825,"RecordedAtTime":1479233210825,"MonitoredVehicleJourney":{"LineRef":{"value":"4415"},"DirectionRef":{"value":"2"},"FramedVehicleJourneyRef":{"DataFrameRef":{"value":"2016-11-15"},"DatedVehicleJourneyRef":"1953"},"OperatorRef":{"value":"HSL"},"Monitored":true,"VehicleLocation":{"Longitude":24.94454,"Latitude":60.28551},"Delay":112,"MonitoredCall":{"StopPointRef":"4510256"},"VehicleRef":{"value":"8924"}}},{"ValidUntilTime":1479233251885,"RecordedAtTime":1479233221885,"MonitoredVehicleJourney":{"LineRef":{"value":"1070T"},"DirectionRef":{"value":"1"},"FramedVehicleJourneyRef":{"DataFrameRef":{"value":"2016-11-15"},"DatedVehicleJourneyRef":"1933"},"OperatorRef":{"value":"HSL"},"Monitored":true,"VehicleLocation":{"Longitude":25.02199,"Latitude":60.23714},"Delay":290,"MonitoredCall":{"StopPointRef":"1382113"},"VehicleRef":{"value":"8949"}}},{"ValidUntilTime":1479233269740,"RecordedAtTime":1479233239740,"MonitoredVehicleJourney":{"LineRef":{"value":"1018"},"DirectionRef":{"value":"2"},"FramedVehicleJourneyRef":{"DataFrameRef":{"value":"2016-11-15"},"DatedVehicleJourneyRef":"2004"},"OperatorRef":{"value":"HSL"},"Monitored":true,"VehicleLocation":{"Longitude":24.86384,"Latitude":60.20556},"Delay":54,"MonitoredCall":{"StopPointRef":"1304131"},"VehicleRef":{"value":"8950"}}},{"ValidUntilTime":1479233262882,"RecordedAtTime":1479233232882,"MonitoredVehicleJourney":{"LineRef":{"value":"1069"},"DirectionRef":{"value":"1"},"FramedVehicleJourneyRef":{"DataFrameRef":{"value":"2016-11-15"},"DatedVehicleJourneyRef":"2003"},"OperatorRef":{"value":"HSL"},"Monitored":true,"VehicleLocation":{"Longitude":24.92182,"Latitude":60.17499},"Delay":12,"MonitoredCall":{"StopPointRef":"1130103"},"VehicleRef":{"value":"11211"}}},{"ValidUntilTime":1479233247676,"RecordedAtTime":1479233217676,"MonitoredVehicleJourney":{"LineRef":{"value":"1069"},"DirectionRef":{"value":"1"},"FramedVehicleJourneyRef":{"DataFrameRef":{"value":"2016-11-15"},"DatedVehicleJourneyRef":"1943"},"OperatorRef":{"value":"HSL"},"Monitored":true,"VehicleLocation":{"Longitude":24.9587,"Latitude":60.21443},"Delay":114,"MonitoredCall":{"StopPointRef":"1250107"},"VehicleRef":{"value":"11214"}}},{"ValidUntilTime":1479233266618,"RecordedAtTime":1479233236618,"MonitoredVehicleJourney":{"LineRef":{"value":"1069"},"DirectionRef":{"value":"1"},"FramedVehicleJourneyRef":{"DataFrameRef":{"value":"2016-11-15"},"DatedVehicleJourneyRef":"1923"},"OperatorRef":{"value":"HSL"},"Monitored":true,"VehicleLocation":{"Longitude":24.99858,"Latitude":60.25674},"Delay":74,"MonitoredCall":{"StopPointRef":"1381107"},"VehicleRef":{"value":"11218"}}},{"ValidUntilTime":1479233270328,"RecordedAtTime":1479233240328,"MonitoredVehicleJourney":{"LineRef":{"value":"1071"},"DirectionRef":{"value":"1"},"FramedVehicleJourneyRef":{"DataFrameRef":{"value":"2016-11-15"},"DatedVehicleJourneyRef":"2009"},"OperatorRef":{"value":"HSL"},"Monitored":true,"VehicleLocation":{"Longitude":24.94317,"Latitude":60.17074},"Delay":0,"MonitoredCall":{"StopPointRef":"1020113"},"VehicleRef":{"value":"11220"}}},{"ValidUntilTime":1479233263306,"RecordedAtTime":1479233233306,"MonitoredVehicleJourney":{"LineRef":{"value":"1071"},"DirectionRef":{"value":"2"},"FramedVehicleJourneyRef":{"DataFrameRef":{"value":"2016-11-15"},"DatedVehicleJourneyRef":"1949"},"OperatorRef":{"value":"HSL"},"Monitored":true,"VehicleLocation":{"Longitude":24.962,"Latitude":60.20037},"Delay":0,"MonitoredCall":{"StopPointRef":"1220127"},"VehicleRef":{"value":"11222"}}},{"ValidUntilTime":1479233250832,"RecordedAtTime":1479233220832,"MonitoredVehicleJourney":{"LineRef":{"value":"1071"},"DirectionRef":{"value":"1"},"FramedVehicleJourneyRef":{"DataFrameRef":{"value":"2016-11-15"},"DatedVehicleJourneyRef":"1954"},"OperatorRef":{"value":"HSL"},"Monitored":true,"VehicleLocation":{"Longitude":24.96186,"Latitude":60.19834},"Delay":50,"MonitoredCall":{"StopPointRef":"1220105"},"VehicleRef":{"value":"11225"}}},{"ValidUntilTime":1479233268336,"RecordedAtTime":1479233238336,"MonitoredVehicleJourney":{"LineRef":{"value":"1071"},"DirectionRef":{"value":"2"},"FramedVehicleJourneyRef":{"DataFrameRef":{"value":"2016-11-15"},"DatedVehicleJourneyRef":"2004"},"OperatorRef":{"value":"HSL"},"Monitored":true,"VehicleLocation":{"Longitude":25.00959,"Latitude":60.23548},"Delay":34,"MonitoredCall":{"StopPointRef":"1383127"},"VehicleRef":{"value":"11227"}}},{"ValidUntilTime":1479233277782,"RecordedAtTime":1479233247782,"MonitoredVehicleJourney":{"LineRef":{"value":"1068"},"DirectionRef":{"value":"1"},"FramedVehicleJourneyRef":{"DataFrameRef":{"value":"2016-11-15"},"DatedVehicleJourneyRef":"1946"},"OperatorRef":{"value":"HSL"},"Monitored":true,"VehicleLocation":{"Longitude":24.98439,"Latitude":60.2179},"Delay":106,"MonitoredCall":{"StopPointRef":"1361103"},"VehicleRef":{"value":"11234"}}},{"ValidUntilTime":1479233251117,"RecordedAtTime":1479233221117,"MonitoredVehicleJourney":{"LineRef":{"value":"1069"},"DirectionRef":{"value":"2"},"FramedVehicleJourneyRef":{"DataFrameRef":{"value":"2016-11-15"},"DatedVehicleJourneyRef":"2000"},"OperatorRef":{"value":"HSL"},"Monitored":true,"VehicleLocation":{"Longitude":24.99479,"Latitude":60.25465},"Delay":64,"MonitoredCall":{"StopPointRef":"1391104"},"VehicleRef":{"value":"11235"}}},{"ValidUntilTime":1479233258634,"RecordedAtTime":1479233228634,"MonitoredVehicleJourney":{"LineRef":{"value":"1068"},"DirectionRef":{"value":"2"},"FramedVehicleJourneyRef":{"DataFrameRef":{"value":"2016-11-15"},"DatedVehicleJourneyRef":"2010"},"OperatorRef":{"value":"HSL"},"Monitored":true,"VehicleLocation":{"Longitude":25.0435,"Latitude":60.23065},"MonitoredCall":{},"VehicleRef":{"value":"11237"}}},{"ValidUntilTime":1479233269444,"RecordedAtTime":1479233239444,"MonitoredVehicleJourney":{"LineRef":{"value":"1068"},"DirectionRef":{"value":"2"},"FramedVehicleJourneyRef":{"DataFrameRef":{"value":"2016-11-15"},"DatedVehicleJourneyRef":"1940"},"OperatorRef":{"value":"HSL"},"Monitored":true,"VehicleLocation":{"Longitude":24.96166,"Latitude":60.19768},"Delay":414,"MonitoredCall":{"StopPointRef":"1220104"},"VehicleRef":{"value":"11241"}}},{"ValidUntilTime":1479233263346,"RecordedAtTime":1479233233346,"MonitoredVehicleJourney":{"LineRef":{"value":"1071"},"DirectionRef":{"value":"2"},"FramedVehicleJourneyRef":{"DataFrameRef":{"value":"2016-11-15"},"DatedVehicleJourneyRef":"2146"},"OperatorRef":{"value":"HSL"},"Monitored":true,"VehicleLocation":{"Longitude":25.05823,"Latitude":60.25744},"MonitoredCall":{},"VehicleRef":{"value":"11242"}}},{"ValidUntilTime":1479233256190,"RecordedAtTime":1479233226190,"MonitoredVehicleJourney":{"LineRef":{"value":"1068"},"DirectionRef":{"value":"1"},"FramedVehicleJourneyRef":{"DataFrameRef":{"value":"2016-11-15"},"DatedVehicleJourneyRef":"2016"},"OperatorRef":{"value":"HSL"},"Monitored":true,"VehicleLocation":{"Longitude":24.94281,"Latitude":60.17139},"MonitoredCall":{},"VehicleRef":{"value":"11244"}}},{"ValidUntilTime":1479233252872,"RecordedAtTime":1479233222872,"MonitoredVehicleJourney":{"LineRef":{"value":"1071"},"DirectionRef":{"value":"1"},"FramedVehicleJourneyRef":{"DataFrameRef":{"value":"2016-11-15"},"DatedVehicleJourneyRef":"1939"},"OperatorRef":{"value":"HSL"},"Monitored":true,"VehicleLocation":{"Longitude":25.00047,"Latitude":60.2311},"Delay":172,"MonitoredCall":{"StopPointRef":"1383138"},"VehicleRef":{"value":"11246"}}},{"ValidUntilTime":1479233261923,"RecordedAtTime":1479233231923,"MonitoredVehicleJourney":{"LineRef":{"value":"1063"},"DirectionRef":{"value":"1"},"FramedVehicleJourneyRef":{"DataFrameRef":{"value":"2016-11-15"},"DatedVehicleJourneyRef":"1937"},"OperatorRef":{"value":"HSL"},"Monitored":true,"VehicleLocation":{"Longitude":24.92811,"Latitude":60.23947},"Delay":4,"MonitoredCall":{"StopPointRef":"1341120"},"VehicleRef":{"value":"11249"}}},{"ValidUntilTime":1479233271937,"RecordedAtTime":1479233241937,"MonitoredVehicleJourney":{"LineRef":{"value":"1063"},"DirectionRef":{"value":"1"},"FramedVehicleJourneyRef":{"DataFrameRef":{"value":"2016-11-15"},"DatedVehicleJourneyRef":"2017"},"OperatorRef":{"value":"HSL"},"Monitored":true,"VehicleLocation":{"Longitude":24.93916,"Latitude":60.172},"MonitoredCall":{},"VehicleRef":{"value":"11252"}}},{"ValidUntilTime":1479233279516,"RecordedAtTime":1479233249516,"MonitoredVehicleJourney":{"LineRef":{"value":"1063"},"DirectionRef":{"value":"2"},"FramedVehicleJourneyRef":{"DataFrameRef":{"value":"2016-11-15"},"DatedVehicleJourneyRef":"1950"},"OperatorRef":{"value":"HSL"},"Monitored":true,"VehicleLocation":{"Longitude":24.90651,"Latitude":60.22174},"Delay":110,"MonitoredCall":{"StopPointRef":"1293157"},"VehicleRef":{"value":"11254"}}},{"ValidUntilTime":1479233263832,"RecordedAtTime":1479233233832,"MonitoredVehicleJourney":{"LineRef":{"value":"1055"},"DirectionRef":{"value":"1"},"FramedVehicleJourneyRef":{"DataFrameRef":{"value":"2016-11-15"},"DatedVehicleJourneyRef":"1952"},"OperatorRef":{"value":"HSL"},"Monitored":true,"VehicleLocation":{"Longitude":24.97792,"Latitude":60.19253},"Delay":126,"MonitoredCall":{"StopPointRef":"1100168"},"VehicleRef":{"value":"11257"}}},{"ValidUntilTime":1479233233274,"RecordedAtTime":1479233203274,"MonitoredVehicleJourney":{"LineRef":{"value":"1055"},"DirectionRef":{"value":"2"},"FramedVehicleJourneyRef":{"DataFrameRef":{"value":"2016-11-15"},"DatedVehicleJourneyRef":"2012"},"OperatorRef":{"value":"HSL"},"Monitored":true,"VehicleLocation":{"Longitude":24.96436,"Latitude":60.21956},"MonitoredCall":{},"VehicleRef":{"value":"11258"}}},{"ValidUntilTime":1479233257154,"RecordedAtTime":1479233227154,"MonitoredVehicleJourney":{"LineRef":{"value":"1055"},"DirectionRef":{"value":"1"},"FramedVehicleJourneyRef":{"DataFrameRef":{"value":"2016-11-15"},"DatedVehicleJourneyRef":"2012"},"OperatorRef":{"value":"HSL"},"Monitored":true,"VehicleLocation":{"Longitude":24.94334,"Latitude":60.17161},"MonitoredCall":{},"VehicleRef":{"value":"11259"}}},{"ValidUntilTime":1479233269417,"RecordedAtTime":1479233239417,"MonitoredVehicleJourney":{"LineRef":{"value":"1055"},"DirectionRef":{"value":"2"},"FramedVehicleJourneyRef":{"DataFrameRef":{"value":"2016-11-15"},"DatedVehicleJourneyRef":"1952"},"OperatorRef":{"value":"HSL"},"Monitored":true,"VehicleLocation":{"Longitude":24.95987,"Latitude":60.18088},"Delay":0,"MonitoredCall":{"StopPointRef":"1100149"},"VehicleRef":{"value":"11261"}}},{"ValidUntilTime":1479233264258,"RecordedAtTime":1479233234258,"MonitoredVehicleJourney":{"LineRef":{"value":"1055"},"DirectionRef":{"value":"2"},"FramedVehicleJourneyRef":{"DataFrameRef":{"value":"2016-11-15"},"DatedVehicleJourneyRef":"2256"},"OperatorRef":{"value":"HSL"},"Monitored":true,"VehicleLocation":{"Longitude":24.96822,"Latitude":60.21447},"MonitoredCall":{},"VehicleRef":{"value":"11262"}}},{"ValidUntilTime":1479233275343,"RecordedAtTime":1479233245343,"MonitoredVehicleJourney":{"LineRef":{"value":"1069"},"DirectionRef":{"value":"2"},"FramedVehicleJourneyRef":{"DataFrameRef":{"value":"2016-11-15"},"DatedVehicleJourneyRef":"2040"},"OperatorRef":{"value":"HSL"},"Monitored":true,"VehicleLocation":{"Longitude":25.01165,"Latitude":60.25009},"MonitoredCall":{},"VehicleRef":{"value":"11263"}}},{"ValidUntilTime":1479233260223,"RecordedAtTime":1479233230223,"MonitoredVehicleJourney":{"LineRef":{"value":"1069"},"DirectionRef":{"value":"2"},"FramedVehicleJourneyRef":{"DataFrameRef":{"value":"2016-11-15"},"DatedVehicleJourneyRef":"1940"},"OperatorRef":{"value":"HSL"},"Monitored":true,"VehicleLocation":{"Longitude":24.95837,"Latitude":60.21396},"Delay":104,"MonitoredCall":{"StopPointRef":"1250108"},"VehicleRef":{"value":"11264"}}},{"ValidUntilTime":1479233277000,"RecordedAtTime":1479233247000,"MonitoredVehicleJourney":{"LineRef":{"value":"1004"},"DirectionRef":{"value":"1"},"FramedVehicleJourneyRef":{"DataFrameRef":{"value":"2016-11-15"},"DatedVehicleJourneyRef":"1915"},"OperatorRef":{"value":"HSL"},"Monitored":true,"VehicleLocation":{"Longitude":24.922353,"Latitude":60.184744},"Bearing":132,"Delay":525,"MonitoredCall":{"Order":23},"VehicleRef":{"value":"RHKL00107"}}},{"ValidUntilTime":1479233275000,"RecordedAtTime":1479233245000,"MonitoredVehicleJourney":{"LineRef":{"value":"1010"},"DirectionRef":{"value":"1"},"FramedVehicleJourneyRef":{"DataFrameRef":{"value":"2016-11-15"},"DatedVehicleJourneyRef":"1953"},"OperatorRef":{"value":"HSL"},"Monitored":true,"VehicleLocation":{"Longitude":24.921453,"Latitude":60.185778},"Bearing":332,"Delay":69,"MonitoredCall":{"Order":10},"VehicleRef":{"value":"RHKL00105"}}},{"ValidUntilTime":1479233279000,"RecordedAtTime":1479233249000,"MonitoredVehicleJourney":{"LineRef":{"value":"1007B"},"DirectionRef":{"value":"2"},"FramedVehicleJourneyRef":{"DataFrameRef":{"value":"2016-11-15"},"DatedVehicleJourneyRef":"1952"},"OperatorRef":{"value":"HSL"},"Monitored":true,"VehicleLocation":{"Longitude":24.926652,"Latitude":60.181814},"Bearing":152,"Delay":-60,"MonitoredCall":{"Order":9},"VehicleRef":{"value":"RHKL00101"}}},{"ValidUntilTime":1479233278000,"RecordedAtTime":1479233248000,"MonitoredVehicleJourney":{"LineRef":{"value":"1007B"},"DirectionRef":{"value":"1"},"FramedVehicleJourneyRef":{"DataFrameRef":{"value":"2016-11-15"},"DatedVehicleJourneyRef":"1751"},"OperatorRef":{"value":"HSL"},"Monitored":true,"VehicleLocation":{"Longitude":24.970154,"Latitude":60.215128},"Bearing":202,"Delay":834,"MonitoredCall":{"Order":17},"VehicleRef":{"value":"RHKL00070"}}},{"ValidUntilTime":1479233278000,"RecordedAtTime":1479233248000,"MonitoredVehicleJourney":{"LineRef":{"value":"1001"},"DirectionRef":{"value":"2"},"FramedVehicleJourneyRef":{"DataFrameRef":{"value":"2016-11-15"},"DatedVehicleJourneyRef":"1920"},"OperatorRef":{"value":"HSL"},"Monitored":true,"VehicleLocation":{"Longitude":24.971198,"Latitude":60.214678},"Bearing":206,"Delay":0,"MonitoredCall":{"Order":10},"VehicleRef":{"value":"RHKL00217"}}},{"ValidUntilTime":1479233278000,"RecordedAtTime":1479233248000,"MonitoredVehicleJourney":{"LineRef":{"value":"1002"},"DirectionRef":{"value":"1"},"FramedVehicleJourneyRef":{"DataFrameRef":{"value":"2016-11-15"},"DatedVehicleJourneyRef":"1948"},"OperatorRef":{"value":"HSL"},"Monitored":true,"VehicleLocation":{"Longitude":24.922917,"Latitude":60.178786},"Bearing":6,"Delay":49,"MonitoredCall":{"Order":13},"VehicleRef":{"value":"RHKL00214"}}},{"ValidUntilTime":1479233278000,"RecordedAtTime":1479233248000,"MonitoredVehicleJourney":{"LineRef":{"value":"1004"},"DirectionRef":{"value":"1"},"FramedVehicleJourneyRef":{"DataFrameRef":{"value":"2016-11-15"},"DatedVehicleJourneyRef":"1900"},"OperatorRef":{"value":"HSL"},"Monitored":true,"VehicleLocation":{"Longitude":24.975534,"Latitude":60.167631},"Bearing":65,"Delay":479,"MonitoredCall":{"Order":23},"VehicleRef":{"value":"RHKL00092"}}},{"ValidUntilTime":1479233276000,"RecordedAtTime":1479233246000,"MonitoredVehicleJourney":{"LineRef":{"value":"1010"},"DirectionRef":{"value":"1"},"FramedVehicleJourneyRef":{"DataFrameRef":{"value":"2016-11-15"},"DatedVehicleJourneyRef":"2004"},"OperatorRef":{"value":"HSL"},"Monitored":true,"VehicleLocation":{"Longitude":24.943691,"Latitude":60.166459},"Bearing":344,"Delay":0,"MonitoredCall":{"Order":5},"VehicleRef":{"value":"RHKL00090"}}},{"ValidUntilTime":1479233279000,"RecordedAtTime":1479233249000,"MonitoredVehicleJourney":{"LineRef":{"value":"1003"},"DirectionRef":{"value":"2"},"FramedVehicleJourneyRef":{"DataFrameRef":{"value":"2016-11-15"},"DatedVehicleJourneyRef":"1935"},"OperatorRef":{"value":"HSL"},"Monitored":true,"VehicleLocation":{"Longitude":24.955837,"Latitude":60.160507},"Bearing":16,"Delay":67,"MonitoredCall":{"Order":22},"VehicleRef":{"value":"RHKL00213"}}},{"ValidUntilTime":1479233277000,"RecordedAtTime":1479233247000,"MonitoredVehicleJourney":{"LineRef":{"value":"1008"},"DirectionRef":{"value":"2"},"FramedVehicleJourneyRef":{"DataFrameRef":{"value":"2016-11-15"},"DatedVehicleJourneyRef":"1955"},"OperatorRef":{"value":"HSL"},"Monitored":true,"VehicleLocation":{"Longitude":24.953484,"Latitude":60.187114},"Bearing":277,"Delay":77,"MonitoredCall":{"Order":10},"VehicleRef":{"value":"RHKL00120"}}},{"ValidUntilTime":1479233277000,"RecordedAtTime":1479233247000,"MonitoredVehicleJourney":{"LineRef":{"value":"1003"},"DirectionRef":{"value":"2"},"FramedVehicleJourneyRef":{"DataFrameRef":{"value":"2016-11-15"},"DatedVehicleJourneyRef":"2035"},"OperatorRef":{"value":"HSL"},"Monitored":true,"VehicleLocation":{"Longitude":24.930767,"Latitude":60.1689},"Bearing":210,"Delay":0,"MonitoredCall":{"Order":1},"VehicleRef":{"value":"RHKL00079"}}},{"ValidUntilTime":1479233278000,"RecordedAtTime":1479233248000,"MonitoredVehicleJourney":{"LineRef":{"value":"1008"},"DirectionRef":{"value":"1"},"FramedVehicleJourneyRef":{"DataFrameRef":{"value":"2016-11-15"},"DatedVehicleJourneyRef":"1942"},"OperatorRef":{"value":"HSL"},"Monitored":true,"VehicleLocation":{"Longitude":24.964273,"Latitude":60.189666},"Bearing":14,"Delay":201,"MonitoredCall":{"Order":17},"VehicleRef":{"value":"RHKL00237"}}},{"ValidUntilTime":1479233278000,"RecordedAtTime":1479233248000,"MonitoredVehicleJourney":{"LineRef":{"value":"1006"},"DirectionRef":{"value":"2"},"FramedVehicleJourneyRef":{"DataFrameRef":{"value":"2016-11-15"},"DatedVehicleJourneyRef":"2003"},"OperatorRef":{"value":"HSL"},"Monitored":true,"VehicleLocation":{"Longitude":24.962158,"Latitude":60.200352},"Bearing":196,"Delay":31,"MonitoredCall":{"Order":5},"VehicleRef":{"value":"RHKL00215"}}},{"ValidUntilTime":1479233278000,"RecordedAtTime":1479233248000,"MonitoredVehicleJourney":{"LineRef":{"value":"1006"},"DirectionRef":{"value":"1"},"FramedVehicleJourneyRef":{"DataFrameRef":{"value":"2016-11-15"},"DatedVehicleJourneyRef":"1958"},"OperatorRef":{"value":"HSL"},"Monitored":true,"VehicleLocation":{"Longitude":24.938807,"Latitude":60.1697},"Bearing":321,"Delay":94,"MonitoredCall":{"Order":8},"VehicleRef":{"value":"RHKL00233"}}},{"ValidUntilTime":1479233278000,"RecordedAtTime":1479233248000,"MonitoredVehicleJourney":{"LineRef":{"value":"1008"},"DirectionRef":{"value":"2"},"FramedVehicleJourneyRef":{"DataFrameRef":{"value":"2016-11-15"},"DatedVehicleJourneyRef":"2007"},"OperatorRef":{"value":"HSL"},"Monitored":true,"VehicleLocation":{"Longitude":24.977233,"Latitude":60.206937},"Bearing":203,"Delay":4,"MonitoredCall":{"Order":2},"VehicleRef":{"value":"RHKL00231"}}},{"ValidUntilTime":1479233276000,"RecordedAtTime":1479233246000,"MonitoredVehicleJourney":{"LineRef":{"value":"1300M"},"DirectionRef":{"value":"2"},"FramedVehicleJourneyRef":{"DataFrameRef":{"value":"2016-11-15"}},"OperatorRef":{"value":"HSL"},"Monitored":true,"VehicleLocation":{"Longitude":24.992396,"Latitude":60.186082},"Bearing":270,"MonitoredCall":{},"VehicleRef":{"value":"metro72"}}},{"ValidUntilTime":1479233277000,"RecordedAtTime":1479233247000,"MonitoredVehicleJourney":{"LineRef":{"value":"1300V"},"DirectionRef":{"value":"1"},"FramedVehicleJourneyRef":{"DataFrameRef":{"value":"2016-11-15"}},"OperatorRef":{"value":"HSL"},"Monitored":true,"VehicleLocation":{"Longitude":25.005006,"Latitude":60.188462},"Bearing":90,"MonitoredCall":{},"VehicleRef":{"value":"metro94"}}},{"ValidUntilTime":1479233278000,"RecordedAtTime":1479233248000,"MonitoredVehicleJourney":{"LineRef":{"value":"1001A"},"DirectionRef":{"value":"2"},"FramedVehicleJourneyRef":{"DataFrameRef":{"value":"2016-11-15"},"DatedVehicleJourneyRef":"0547"},"OperatorRef":{"value":"HSL"},"Monitored":true,"VehicleLocation":{"Longitude":24.933088,"Latitude":60.17445},"Bearing":336,"Delay":50656,"MonitoredCall":{"Order":2},"VehicleRef":{"value":"RHKL00091"}}},{"ValidUntilTime":1479233278000,"RecordedAtTime":1479233248000,"MonitoredVehicleJourney":{"LineRef":{"value":"1003"},"DirectionRef":{"value":"2"},"FramedVehicleJourneyRef":{"DataFrameRef":{"value":"2016-11-15"},"DatedVehicleJourneyRef":"1845"},"OperatorRef":{"value":"HSL"},"Monitored":true,"VehicleLocation":{"Longitude":24.950013,"Latitude":60.178031},"Bearing":199,"Delay":250,"MonitoredCall":{"Order":22},"VehicleRef":{"value":"RHKL00032"}}},{"ValidUntilTime":1479233278000,"RecordedAtTime":1479233248000,"MonitoredVehicleJourney":{"LineRef":{"value":"1002"},"DirectionRef":{"value":"2"},"FramedVehicleJourneyRef":{"DataFrameRef":{"value":"2016-11-15"},"DatedVehicleJourneyRef":"1949"},"OperatorRef":{"value":"HSL"},"Monitored":true,"VehicleLocation":{"Longitude":24.935345,"Latitude":60.168697},"Bearing":64,"Delay":202,"MonitoredCall":{"Order":11},"VehicleRef":{"value":"RHKL00238"}}},{"ValidUntilTime":1479233276000,"RecordedAtTime":1479233246000,"MonitoredVehicleJourney":{"LineRef":{"value":"1006"},"DirectionRef":{"value":"2"},"FramedVehicleJourneyRef":{"DataFrameRef":{"value":"2016-11-15"},"DatedVehicleJourneyRef":"1951"},"OperatorRef":{"value":"HSL"},"Monitored":true,"VehicleLocation":{"Longitude":24.95042,"Latitude":60.17855},"Bearing":177,"Delay":127,"MonitoredCall":{"Order":13},"VehicleRef":{"value":"RHKL00201"}}},{"ValidUntilTime":1479233275000,"RecordedAtTime":1479233245000,"MonitoredVehicleJourney":{"LineRef":{"value":"1300M"},"DirectionRef":{"value":"1"},"FramedVehicleJourneyRef":{"DataFrameRef":{"value":"2016-11-15"}},"OperatorRef":{"value":"HSL"},"Monitored":true,"VehicleLocation":{"Longitude":25.030097,"Latitude":60.194419},"Bearing":90,"MonitoredCall":{},"VehicleRef":{"value":"metro79"}}},{"ValidUntilTime":1479233275000,"RecordedAtTime":1479233245000,"MonitoredVehicleJourney":{"LineRef":{"value":"1300V"},"DirectionRef":{"value":"1"},"FramedVehicleJourneyRef":{"DataFrameRef":{"value":"2016-11-15"}},"OperatorRef":{"value":"HSL"},"Monitored":true,"VehicleLocation":{"Longitude":25.07695,"Latitude":60.209853},"Bearing":90,"MonitoredCall":{},"VehicleRef":{"value":"metro77"}}},{"ValidUntilTime":1479233277000,"RecordedAtTime":1479233247000,"MonitoredVehicleJourney":{"LineRef":{"value":"1300V"},"DirectionRef":{"value":"2"},"FramedVehicleJourneyRef":{"DataFrameRef":{"value":"2016-11-15"}},"OperatorRef":{"value":"HSL"},"Monitored":true,"VehicleLocation":{"Longitude":24.953889,"Latitude":60.184589},"Bearing":270,"MonitoredCall":{},"VehicleRef":{"value":"metro73"}}},{"ValidUntilTime":1479233278000,"RecordedAtTime":1479233248000,"MonitoredVehicleJourney":{"LineRef":{"value":"1004"},"DirectionRef":{"value":"1"},"FramedVehicleJourneyRef":{"DataFrameRef":{"value":"2016-11-15"},"DatedVehicleJourneyRef":"2002"},"OperatorRef":{"value":"HSL"},"Monitored":true,"VehicleLocation":{"Longitude":24.95304,"Latitude":60.169123},"Bearing":267,"Delay":-5,"MonitoredCall":{"Order":7},"VehicleRef":{"value":"RHKL00087"}}},{"ValidUntilTime":1479233264000,"RecordedAtTime":1479233234000,"MonitoredVehicleJourney":{"LineRef":{"value":"1006"},"DirectionRef":{"value":"1"},"FramedVehicleJourneyRef":{"DataFrameRef":{"value":"2016-11-15"},"DatedVehicleJourneyRef":"1958"},"OperatorRef":{"value":"HSL"},"Monitored":true,"VehicleLocation":{"Longitude":24.923706,"Latitude":60.179778},"Bearing":203,"Delay":94,"MonitoredCall":{"Order":8},"VehicleRef":{"value":"RHKL00084"}}},{"ValidUntilTime":1479233278000,"RecordedAtTime":1479233248000,"MonitoredVehicleJourney":{"LineRef":{"value":"1004"},"DirectionRef":{"value":"2"},"FramedVehicleJourneyRef":{"DataFrameRef":{"value":"2016-11-15"},"DatedVehicleJourneyRef":"2014"},"OperatorRef":{"value":"HSL"},"Monitored":true,"VehicleLocation":{"Longitude":24.872621,"Latitude":60.194475},"Bearing":111,"Delay":0,"MonitoredCall":{"Order":1},"VehicleRef":{"value":"RHKL00083"}}},{"ValidUntilTime":1479233279000,"RecordedAtTime":1479233249000,"MonitoredVehicleJourney":{"LineRef":{"value":"1010"},"DirectionRef":{"value":"2"},"FramedVehicleJourneyRef":{"DataFrameRef":{"value":"2016-11-15"},"DatedVehicleJourneyRef":"1948"},"OperatorRef":{"value":"HSL"},"Monitored":true,"VehicleLocation":{"Longitude":24.937817,"Latitude":60.170289},"Bearing":144,"Delay":-34,"MonitoredCall":{"Order":14},"VehicleRef":{"value":"RHKL00081"}}},{"ValidUntilTime":1479233270000,"RecordedAtTime":1479233240000,"MonitoredVehicleJourney":{"LineRef":{"value":"1003"},"DirectionRef":{"value":"2"},"FramedVehicleJourneyRef":{"DataFrameRef":{"value":"2016-11-15"},"DatedVehicleJourneyRef":"2015"},"OperatorRef":{"value":"HSL"},"Monitored":true,"VehicleLocation":{"Longitude":24.908043,"Latitude":60.162918},"Bearing":3,"Delay":0,"MonitoredCall":{"Order":1},"VehicleRef":{"value":"RHKL00089"}}},{"ValidUntilTime":1479233278000,"RecordedAtTime":1479233248000,"MonitoredVehicleJourney":{"LineRef":{"value":"1008"},"DirectionRef":{"value":"2"},"FramedVehicleJourneyRef":{"DataFrameRef":{"value":"2016-11-15"},"DatedVehicleJourneyRef":"1945"},"OperatorRef":{"value":"HSL"},"Monitored":true,"VehicleLocation":{"Longitude":24.922289,"Latitude":60.176251},"Bearing":155,"Delay":127,"MonitoredCall":{"Order":16},"VehicleRef":{"value":"RHKL00042"}}},{"ValidUntilTime":1479233277000,"RecordedAtTime":1479233247000,"MonitoredVehicleJourney":{"LineRef":{"value":"1300M"},"DirectionRef":{"value":"2"},"FramedVehicleJourneyRef":{"DataFrameRef":{"value":"2016-11-15"}},"OperatorRef":{"value":"HSL"},"Monitored":true,"VehicleLocation":{"Longitude":25.108873,"Latitude":60.20815},"Bearing":270,"MonitoredCall":{},"VehicleRef":{"value":"metro80"}}},{"ValidUntilTime":1479233278000,"RecordedAtTime":1479233248000,"MonitoredVehicleJourney":{"LineRef":{"value":"1002"},"DirectionRef":{"value":"1"},"FramedVehicleJourneyRef":{"DataFrameRef":{"value":"2016-11-15"},"DatedVehicleJourneyRef":"1448"},"OperatorRef":{"value":"HSL"},"Monitored":true,"VehicleLocation":{"Longitude":24.971448,"Latitude":60.214595},"Bearing":26,"Delay":3845,"MonitoredCall":{"Order":18},"VehicleRef":{"value":"RHKL00206"}}},{"ValidUntilTime":1479233278000,"RecordedAtTime":1479233248000,"MonitoredVehicleJourney":{"LineRef":{"value":"1007A"},"DirectionRef":{"value":"2"},"FramedVehicleJourneyRef":{"DataFrameRef":{"value":"2016-11-15"},"DatedVehicleJourneyRef":"2034"},"OperatorRef":{"value":"HSL"},"Monitored":true,"VehicleLocation":{"Longitude":24.930368,"Latitude":60.176824},"Bearing":328,"Delay":0,"MonitoredCall":{"Order":1},"VehicleRef":{"value":"RHKL00067"}}},{"ValidUntilTime":1479233277000,"RecordedAtTime":1479233247000,"MonitoredVehicleJourney":{"LineRef":{"value":"1300M"},"DirectionRef":{"value":"1"},"FramedVehicleJourneyRef":{"DataFrameRef":{"value":"2016-11-15"}},"OperatorRef":{"value":"HSL"},"Monitored":true,"VehicleLocation":{"Longitude":24.914453,"Latitude":60.162992},"Bearing":90,"MonitoredCall":{},"VehicleRef":{"value":"metro76"}}},{"ValidUntilTime":1479233278000,"RecordedAtTime":1479233248000,"MonitoredVehicleJourney":{"LineRef":{"value":"1006"},"DirectionRef":{"value":"1"},"FramedVehicleJourneyRef":{"DataFrameRef":{"value":"2016-11-15"},"DatedVehicleJourneyRef":"1857"},"OperatorRef":{"value":"HSL"},"Monitored":true,"VehicleLocation":{"Longitude":24.913257,"Latitude":60.163375},"Bearing":265,"Delay":420,"MonitoredCall":{"Order":22},"VehicleRef":{"value":"RHKL00226"}}},{"ValidUntilTime":1479233232000,"RecordedAtTime":1479233202000,"MonitoredVehicleJourney":{"LineRef":{"value":"1006T"},"DirectionRef":{"value":"1"},"FramedVehicleJourneyRef":{"DataFrameRef":{"value":"2016-11-15"},"DatedVehicleJourneyRef":"1720"},"OperatorRef":{"value":"HSL"},"Monitored":true,"VehicleLocation":{"Longitude":24.97054,"Latitude":60.214757},"Bearing":343,"Delay":411,"MonitoredCall":{"Order":24},"VehicleRef":{"value":"RHKL00402"}}},{"ValidUntilTime":1479233278000,"RecordedAtTime":1479233248000,"MonitoredVehicleJourney":{"LineRef":{"value":"1007A"},"DirectionRef":{"value":"2"},"FramedVehicleJourneyRef":{"DataFrameRef":{"value":"2016-11-15"},"DatedVehicleJourneyRef":"1958"},"OperatorRef":{"value":"HSL"},"Monitored":true,"VehicleLocation":{"Longitude":24.959757,"Latitude":60.193071},"Bearing":134,"Delay":107,"MonitoredCall":{"Order":9},"VehicleRef":{"value":"RHKL00069"}}},{"ValidUntilTime":1479233278000,"RecordedAtTime":1479233248000,"MonitoredVehicleJourney":{"LineRef":{"value":"1005"},"DirectionRef":{"value":"1"},"FramedVehicleJourneyRef":{"DataFrameRef":{"value":"2016-11-15"},"DatedVehicleJourneyRef":"1652"},"OperatorRef":{"value":"HSL"},"Monitored":true,"VehicleLocation":{"Longitude":24.969939,"Latitude":60.21448},"Bearing":213,"Delay":1868,"MonitoredCall":{"Order":9},"VehicleRef":{"value":"RHKL00401"}}},{"ValidUntilTime":1479233278000,"RecordedAtTime":1479233248000,"MonitoredVehicleJourney":{"LineRef":{"value":"1003"},"DirectionRef":{"value":"2"},"FramedVehicleJourneyRef":{"DataFrameRef":{"value":"2016-11-15"},"DatedVehicleJourneyRef":"2015"},"OperatorRef":{"value":"HSL"},"Monitored":true,"VehicleLocation":{"Longitude":24.931187,"Latitude":60.192683},"Bearing":71,"Delay":0,"MonitoredCall":{"Order":1},"VehicleRef":{"value":"RHKL00220"}}},{"ValidUntilTime":1479233279000,"RecordedAtTime":1479233249000,"MonitoredVehicleJourney":{"LineRef":{"value":"1004"},"DirectionRef":{"value":"2"},"FramedVehicleJourneyRef":{"DataFrameRef":{"value":"2016-11-15"},"DatedVehicleJourneyRef":"1930"},"OperatorRef":{"value":"HSL"},"Monitored":true,"VehicleLocation":{"Longitude":24.973798,"Latitude":60.167374},"Bearing":212,"Delay":114,"MonitoredCall":{"Order":23},"VehicleRef":{"value":"RHKL00114"}}},{"ValidUntilTime":1479233278000,"RecordedAtTime":1479233248000,"MonitoredVehicleJourney":{"LineRef":{"value":"1008"},"DirectionRef":{"value":"2"},"FramedVehicleJourneyRef":{"DataFrameRef":{"value":"2016-11-15"},"DatedVehicleJourneyRef":"2008"},"OperatorRef":{"value":"HSL"},"Monitored":true,"VehicleLocation":{"Longitude":24.978361,"Latitude":60.208219},"Bearing":198,"Delay":0,"MonitoredCall":{"Order":1},"VehicleRef":{"value":"RHKL00222"}}},{"ValidUntilTime":1479233278000,"RecordedAtTime":1479233248000,"MonitoredVehicleJourney":{"LineRef":{"value":"1001A"},"DirectionRef":{"value":"2"},"FramedVehicleJourneyRef":{"DataFrameRef":{"value":"2016-11-15"},"DatedVehicleJourneyRef":"0547"},"OperatorRef":{"value":"HSL"},"Monitored":true,"VehicleLocation":{"Longitude":24.972407,"Latitude":60.215421},"Bearing":23,"Delay":50656,"MonitoredCall":{"Order":2},"VehicleRef":{"value":"RHKL00223"}}},{"ValidUntilTime":1479233277000,"RecordedAtTime":1479233247000,"MonitoredVehicleJourney":{"LineRef":{"value":"1003"},"DirectionRef":{"value":"1"},"FramedVehicleJourneyRef":{"DataFrameRef":{"value":"2016-11-15"},"DatedVehicleJourneyRef":"1946"},"OperatorRef":{"value":"HSL"},"Monitored":true,"VehicleLocation":{"Longitude":24.949601,"Latitude":60.180674},"Bearing":320,"Delay":90,"MonitoredCall":{"Order":15},"VehicleRef":{"value":"RHKL00229"}}},{"ValidUntilTime":1479233275000,"RecordedAtTime":1479233245000,"MonitoredVehicleJourney":{"LineRef":{"value":"1300V"},"DirectionRef":{"value":"2"},"FramedVehicleJourneyRef":{"DataFrameRef":{"value":"2016-11-15"}},"OperatorRef":{"value":"HSL"},"Monitored":true,"VehicleLocation":{"Longitude":25.055728,"Latitude":60.208674},"Bearing":270,"MonitoredCall":{},"VehicleRef":{"value":"metro93"}}},{"ValidUntilTime":1479233279000,"RecordedAtTime":1479233249000,"MonitoredVehicleJourney":{"LineRef":{"value":"1002"},"DirectionRef":{"value":"2"},"FramedVehicleJourneyRef":{"DataFrameRef":{"value":"2016-11-15"},"DatedVehicleJourneyRef":"1939"},"OperatorRef":{"value":"HSL"},"Monitored":true,"VehicleLocation":{"Longitude":24.944125,"Latitude":60.15819},"Bearing":264,"Delay":260,"MonitoredCall":{"Order":18},"VehicleRef":{"value":"RHKL00240"}}},{"ValidUntilTime":1479233277000,"RecordedAtTime":1479233247000,"MonitoredVehicleJourney":{"LineRef":{"value":"1300M"},"DirectionRef":{"value":"2"},"FramedVehicleJourneyRef":{"DataFrameRef":{"value":"2016-11-15"}},"OperatorRef":{"value":"HSL"},"Monitored":true,"VehicleLocation":{"Longitude":24.922079,"Latitude":60.163969},"Bearing":270,"MonitoredCall":{},"VehicleRef":{"value":"metro78"}}},{"ValidUntilTime":1479233275000,"RecordedAtTime":1479233245000,"MonitoredVehicleJourney":{"LineRef":{"value":"1006"},"DirectionRef":{"value":"1"},"FramedVehicleJourneyRef":{"DataFrameRef":{"value":"2016-11-15"},"DatedVehicleJourneyRef":"1857"},"OperatorRef":{"value":"HSL"},"Monitored":true,"VehicleLocation":{"Longitude":24.971797,"Latitude":60.215172},"Bearing":0,"Delay":420,"MonitoredCall":{"Order":22},"VehicleRef":{"value":"RHKL00999"}}},{"ValidUntilTime":1479233278000,"RecordedAtTime":1479233248000,"MonitoredVehicleJourney":{"LineRef":{"value":"1004"},"DirectionRef":{"value":"1"},"FramedVehicleJourneyRef":{"DataFrameRef":{"value":"2016-11-15"},"DatedVehicleJourneyRef":"1946"},"OperatorRef":{"value":"HSL"},"Monitored":true,"VehicleLocation":{"Longitude":24.913807,"Latitude":60.191069},"Bearing":309,"Delay":104,"MonitoredCall":{"Order":16},"VehicleRef":{"value":"RHKL00122"}}},{"ValidUntilTime":1479233266000,"RecordedAtTime":1479233236000,"MonitoredVehicleJourney":{"LineRef":{"value":"1001"},"DirectionRef":{"value":"2"},"FramedVehicleJourneyRef":{"DataFrameRef":{"value":"2016-11-15"},"DatedVehicleJourneyRef":"1920"},"OperatorRef":{"value":"HSL"},"Monitored":true,"VehicleLocation":{"Longitude":24.927282,"Latitude":60.199865},"Bearing":347,"Delay":0,"MonitoredCall":{"Order":10},"VehicleRef":{"value":"RHKL00093"}}},{"ValidUntilTime":1479233233000,"RecordedAtTime":1479233203000,"MonitoredVehicleJourney":{"LineRef":{"value":"1004"},"DirectionRef":{"value":"1"},"FramedVehicleJourneyRef":{"DataFrameRef":{"value":"2016-11-15"},"DatedVehicleJourneyRef":"1946"},"OperatorRef":{"value":"HSL"},"Monitored":true,"VehicleLocation":{"Longitude":24.930183,"Latitude":60.19252},"Bearing":2,"Delay":35,"MonitoredCall":{"Order":15},"VehicleRef":{"value":"RHKL00059"}}},{"ValidUntilTime":1479233265000,"RecordedAtTime":1479233235000,"MonitoredVehicleJourney":{"LineRef":{"value":"1004"},"DirectionRef":{"value":"1"},"FramedVehicleJourneyRef":{"DataFrameRef":{"value":"2016-11-15"},"DatedVehicleJourneyRef":"1900"},"OperatorRef":{"value":"HSL"},"Monitored":true,"VehicleLocation":{"Longitude":24.92408,"Latitude":60.183431},"Bearing":143,"Delay":479,"MonitoredCall":{"Order":23},"VehicleRef":{"value":"RHKL00116"}}},{"ValidUntilTime":1479233253000,"RecordedAtTime":1479233223000,"MonitoredVehicleJourney":{"LineRef":{"value":"1002"},"DirectionRef":{"value":"2"},"FramedVehicleJourneyRef":{"DataFrameRef":{"value":"2016-11-15"},"DatedVehicleJourneyRef":"1949"},"OperatorRef":{"value":"HSL"},"Monitored":true,"VehicleLocation":{"Longitude":24.900973,"Latitude":60.199077},"Bearing":337,"Delay":202,"MonitoredCall":{"Order":11},"VehicleRef":{"value":"RHKL00077"}}},{"ValidUntilTime":1479233273000,"RecordedAtTime":1479233243000,"MonitoredVehicleJourney":{"LineRef":{"value":"1003"},"DirectionRef":{"value":"2"},"FramedVehicleJourneyRef":{"DataFrameRef":{"value":"2016-11-15"},"DatedVehicleJourneyRef":"1935"},"OperatorRef":{"value":"HSL"},"Monitored":true,"VehicleLocation":{"Longitude":24.953214,"Latitude":60.172082},"Bearing":328,"Delay":67,"MonitoredCall":{"Order":22},"VehicleRef":{"value":"RHKL00071"}}},{"ValidUntilTime":1479233268000,"RecordedAtTime":1479233238000,"MonitoredVehicleJourney":{"LineRef":{"value":"1002"},"DirectionRef":{"value":"1"},"FramedVehicleJourneyRef":{"DataFrameRef":{"value":"2016-11-15"},"DatedVehicleJourneyRef":"1948"},"OperatorRef":{"value":"HSL"},"Monitored":true,"VehicleLocation":{"Longitude":24.94086,"Latitude":60.191176},"Bearing":96,"Delay":49,"MonitoredCall":{"Order":13},"VehicleRef":{"value":"RHKL00210"}}},{"ValidUntilTime":1479233279000,"RecordedAtTime":1479233249000,"MonitoredVehicleJourney":{"LineRef":{"value":"1006T"},"DirectionRef":{"value":"1"},"FramedVehicleJourneyRef":{"DataFrameRef":{"value":"2016-11-15"},"DatedVehicleJourneyRef":"1720"},"OperatorRef":{"value":"HSL"},"Monitored":true,"VehicleLocation":{"Longitude":24.97099,"Latitude":60.214467},"Bearing":206,"Delay":411,"MonitoredCall":{"Order":24},"VehicleRef":{"value":"RHKL00224"}}},{"ValidUntilTime":1479233259000,"RecordedAtTime":1479233229000,"MonitoredVehicleJourney":{"LineRef":{"value":"1010"},"DirectionRef":{"value":"2"},"FramedVehicleJourneyRef":{"DataFrameRef":{"value":"2016-11-15"},"DatedVehicleJourneyRef":"1948"},"OperatorRef":{"value":"HSL"},"Monitored":true,"VehicleLocation":{"Longitude":24.892894,"Latitude":60.208218},"Bearing":13,"Delay":-34,"MonitoredCall":{"Order":14},"VehicleRef":{"value":"RHKL00086"}}},{"ValidUntilTime":1479233243000,"RecordedAtTime":1479233213000,"MonitoredVehicleJourney":{"LineRef":{"value":"1010"},"DirectionRef":{"value":"2"},"FramedVehicleJourneyRef":{"DataFrameRef":{"value":"2016-11-15"},"DatedVehicleJourneyRef":"1948"},"OperatorRef":{"value":"HSL"},"Monitored":true,"VehicleLocation":{"Longitude":24.872544,"Latitude":60.19452},"Bearing":92,"Delay":-34,"MonitoredCall":{"Order":14},"VehicleRef":{"value":"RHKL00072"}}},{"ValidUntilTime":1479233277000,"RecordedAtTime":1479233247000,"MonitoredVehicleJourney":{"LineRef":{"value":"1002"},"DirectionRef":{"value":"1"},"FramedVehicleJourneyRef":{"DataFrameRef":{"value":"2016-11-15"},"DatedVehicleJourneyRef":"1448"},"OperatorRef":{"value":"HSL"},"Monitored":true,"VehicleLocation":{"Longitude":24.943381,"Latitude":60.166644},"Bearing":10,"Delay":3845,"MonitoredCall":{"Order":18},"VehicleRef":{"value":"RHKL00218"}}},{"ValidUntilTime":1479233274000,"RecordedAtTime":1479233244000,"MonitoredVehicleJourney":{"LineRef":{"value":"1001A"},"DirectionRef":{"value":"2"},"FramedVehicleJourneyRef":{"DataFrameRef":{"value":"2016-11-15"},"DatedVehicleJourneyRef":"0547"},"OperatorRef":{"value":"HSL"},"Monitored":true,"VehicleLocation":{"Longitude":24.930588,"Latitude":60.192608},"Bearing":250,"Delay":50656,"MonitoredCall":{"Order":2},"VehicleRef":{"value":"RHKL00111"}}},{"ValidUntilTime":1479233268000,"RecordedAtTime":1479233238000,"MonitoredVehicleJourney":{"LineRef":{"value":"1001"},"DirectionRef":{"value":"2"},"FramedVehicleJourneyRef":{"DataFrameRef":{"value":"2016-11-15"},"DatedVehicleJourneyRef":"1920"},"OperatorRef":{"value":"HSL"},"Monitored":true,"VehicleLocation":{"Longitude":24.953517,"Latitude":60.169761},"Bearing":185,"Delay":0,"MonitoredCall":{"Order":10},"VehicleRef":{"value":"RHKL00227"}}},{"ValidUntilTime":1479233274000,"RecordedAtTime":1479233244000,"MonitoredVehicleJourney":{"LineRef":{"value":"1002"},"DirectionRef":{"value":"1"},"FramedVehicleJourneyRef":{"DataFrameRef":{"value":"2016-11-15"},"DatedVehicleJourneyRef":"1948"},"OperatorRef":{"value":"HSL"},"Monitored":true,"VehicleLocation":{"Longitude":24.946459,"Latitude":60.161353},"Bearing":174,"Delay":49,"MonitoredCall":{"Order":13},"VehicleRef":{"value":"RHKL00110"}}},{"ValidUntilTime":1479233277000,"RecordedAtTime":1479233247000,"MonitoredVehicleJourney":{"LineRef":{"value":"1300M"},"DirectionRef":{"value":"1"},"FramedVehicleJourneyRef":{"DataFrameRef":{"value":"2016-11-15"}},"OperatorRef":{"value":"HSL"},"Monitored":true,"VehicleLocation":{"Longitude":25.12827,"Latitude":60.204835},"Bearing":90,"MonitoredCall":{},"VehicleRef":{"value":"metro71"}}},{"ValidUntilTime":1479233276091,"RecordedAtTime":1479233246091,"MonitoredVehicleJourney":{"LineRef":{"value":"3002P"},"DirectionRef":{"value":"1"},"FramedVehicleJourneyRef":{"DataFrameRef":{"value":"2016-11-15"},"DatedVehicleJourneyRef":"1916"},"OperatorRef":{"value":"HSL"},"Monitored":true,"VehicleLocation":{"Longitude":24.95281,"Latitude":60.22233},"Bearing":236,"Delay":0,"MonitoredCall":{"Order":24},"VehicleRef":{"value":"H8756"}}},{"ValidUntilTime":1479233275942,"RecordedAtTime":1479233245942,"MonitoredVehicleJourney":{"LineRef":{"value":"3001Z"},"DirectionRef":{"value":"2"},"FramedVehicleJourneyRef":{"DataFrameRef":{"value":"2016-11-15"},"DatedVehicleJourneyRef":"1921"},"OperatorRef":{"value":"HSL"},"Monitored":true,"VehicleLocation":{"Longitude":25.05335,"Latitude":60.31261},"Bearing":192,"Delay":0,"MonitoredCall":{"Order":5},"VehicleRef":{"value":"H9860"}}},{"ValidUntilTime":1479233276141,"RecordedAtTime":1479233246141,"MonitoredVehicleJourney":{"LineRef":{"value":"3001I"},"DirectionRef":{"value":"1"},"FramedVehicleJourneyRef":{"DataFrameRef":{"value":"2016-11-15"},"DatedVehicleJourneyRef":"1926"},"OperatorRef":{"value":"HSL"},"Monitored":true,"VehicleLocation":{"Longitude":24.85429,"Latitude":60.26694},"Bearing":177,"Delay":0,"MonitoredCall":{"Order":18},"VehicleRef":{"value":"H9161"}}},{"ValidUntilTime":1479233276050,"RecordedAtTime":1479233246050,"MonitoredVehicleJourney":{"LineRef":{"value":"3001R"},"DirectionRef":{"value":"2"},"FramedVehicleJourneyRef":{"DataFrameRef":{"value":"2016-11-15"},"DatedVehicleJourneyRef":"1925"},"OperatorRef":{"value":"HSL"},"Monitored":true,"VehicleLocation":{"Longitude":24.98357,"Latitude":60.2372},"Bearing":224,"Delay":120,"MonitoredCall":{"Order":9},"VehicleRef":{"value":"H9710"}}},{"ValidUntilTime":1479233277000,"RecordedAtTime":1479233247000,"MonitoredVehicleJourney":{"LineRef":{"value":"1300M"},"DirectionRef":{"value":"1"},"FramedVehicleJourneyRef":{"DataFrameRef":{"value":"2016-11-15"}},"OperatorRef":{"value":"HSL"},"Monitored":true,"VehicleLocation":{"Longitude":24.956476,"Latitude":60.184979},"Bearing":90,"MonitoredCall":{},"VehicleRef":{"value":"metro87"}}},{"ValidUntilTime":1479233276197,"RecordedAtTime":1479233246197,"MonitoredVehicleJourney":{"LineRef":{"value":"3002P"},"DirectionRef":{"value":"1"},"FramedVehicleJourneyRef":{"DataFrameRef":{"value":"2016-11-15"},"DatedVehicleJourneyRef":"1931"},"OperatorRef":{"value":"HSL"},"Monitored":true,"VehicleLocation":{"Longitude":24.75811,"Latitude":60.51527},"Bearing":284,"Delay":0,"MonitoredCall":{"Order":16},"VehicleRef":{"value":"H8757"}}},{"ValidUntilTime":1479233275979,"RecordedAtTime":1479233245979,"MonitoredVehicleJourney":{"LineRef":{"value":"3001N"},"DirectionRef":{"value":"1"},"FramedVehicleJourneyRef":{"DataFrameRef":{"value":"2016-11-15"},"DatedVehicleJourneyRef":"1933"},"OperatorRef":{"value":"HSL"},"Monitored":true,"VehicleLocation":{"Longitude":25.10081,"Latitude":60.38931},"Bearing":10,"Delay":0,"MonitoredCall":{"Order":15},"VehicleRef":{"value":"H9571"}}},{"ValidUntilTime":1479233276077,"RecordedAtTime":1479233246077,"MonitoredVehicleJourney":{"LineRef":{"value":"3001N"},"DirectionRef":{"value":"2"},"FramedVehicleJourneyRef":{"DataFrameRef":{"value":"2016-11-15"},"DatedVehicleJourneyRef":"1932"},"OperatorRef":{"value":"HSL"},"Monitored":true,"VehicleLocation":{"Longitude":24.93392,"Latitude":60.19253},"Bearing":177,"Delay":60,"MonitoredCall":{"Order":15},"VehicleRef":{"value":"H9562"}}},{"ValidUntilTime":1479233276097,"RecordedAtTime":1479233246097,"MonitoredVehicleJourney":{"LineRef":{"value":"3002Y"},"DirectionRef":{"value":"1"},"FramedVehicleJourneyRef":{"DataFrameRef":{"value":"2016-11-15"},"DatedVehicleJourneyRef":"1937"},"OperatorRef":{"value":"HSL"},"Monitored":true,"VehicleLocation":{"Longitude":24.46599,"Latitude":60.11662},"Bearing":252,"Delay":120,"MonitoredCall":{"Order":7},"VehicleRef":{"value":"H8569"}}},{"ValidUntilTime":1479233276041,"RecordedAtTime":1479233246041,"MonitoredVehicleJourney":{"LineRef":{"value":"3002U"},"DirectionRef":{"value":"2"},"FramedVehicleJourneyRef":{"DataFrameRef":{"value":"2016-11-15"},"DatedVehicleJourneyRef":"1938"},"OperatorRef":{"value":"HSL"},"Monitored":true,"VehicleLocation":{"Longitude":24.84426,"Latitude":60.22178},"Bearing":50,"Delay":0,"MonitoredCall":{"Order":13},"VehicleRef":{"value":"H8568"}}},{"ValidUntilTime":1479233275931,"RecordedAtTime":1479233245931,"MonitoredVehicleJourney":{"LineRef":{"value":"3001R"},"DirectionRef":{"value":"1"},"FramedVehicleJourneyRef":{"DataFrameRef":{"value":"2016-11-15"},"DatedVehicleJourneyRef":"1942"},"OperatorRef":{"value":"HSL"},"Monitored":true,"VehicleLocation":{"Longitude":25.10282,"Latitude":60.45236},"Bearing":352,"Delay":0,"MonitoredCall":{"Order":5},"VehicleRef":{"value":"H9719"}}},{"ValidUntilTime":1479233276029,"RecordedAtTime":1479233246029,"MonitoredVehicleJourney":{"LineRef":{"value":"3001I"},"DirectionRef":{"value":"1"},"FramedVehicleJourneyRef":{"DataFrameRef":{"value":"2016-11-15"},"DatedVehicleJourneyRef":"1941"},"OperatorRef":{"value":"HSL"},"Monitored":true,"VehicleLocation":{"Longitude":24.97186898,"Latitude":60.31902329},"Bearing":207,"Delay":0,"MonitoredCall":{"Order":12},"VehicleRef":{"value":"H9162"}}},{"ValidUntilTime":1479233275962,"RecordedAtTime":1479233245962,"MonitoredVehicleJourney":{"LineRef":{"value":"3002U"},"DirectionRef":{"value":"1"},"FramedVehicleJourneyRef":{"DataFrameRef":{"value":"2016-11-15"},"DatedVehicleJourneyRef":"1943"},"OperatorRef":{"value":"HSL"},"Monitored":true,"VehicleLocation":{"Longitude":24.66472,"Latitude":60.20681},"Bearing":248,"Delay":60,"MonitoredCall":{"Order":10},"VehicleRef":{"value":"H8573"}}},{"ValidUntilTime":1479233276005,"RecordedAtTime":1479233246005,"MonitoredVehicleJourney":{"LineRef":{"value":"3001N"},"DirectionRef":{"value":"2"},"FramedVehicleJourneyRef":{"DataFrameRef":{"value":"2016-11-15"},"DatedVehicleJourneyRef":"1947"},"OperatorRef":{"value":"HSL"},"Monitored":true,"VehicleLocation":{"Longitude":25.01656,"Latitude":60.25445},"Bearing":217,"Delay":60,"MonitoredCall":{"Order":9},"VehicleRef":{"value":"H9568"}}},{"ValidUntilTime":1479233276122,"RecordedAtTime":1479233246122,"MonitoredVehicleJourney":{"LineRef":{"value":"3002P"},"DirectionRef":{"value":"1"},"FramedVehicleJourneyRef":{"DataFrameRef":{"value":"2016-11-15"},"DatedVehicleJourneyRef":"1946"},"OperatorRef":{"value":"HSL"},"Monitored":true,"VehicleLocation":{"Longitude":24.84678,"Latitude":60.28755},"Bearing":343,"Delay":60,"MonitoredCall":{"Order":11},"VehicleRef":{"value":"H8758"}}},{"ValidUntilTime":1479233276068,"RecordedAtTime":1479233246068,"MonitoredVehicleJourney":{"LineRef":{"value":"3001I"},"DirectionRef":{"value":"1"},"FramedVehicleJourneyRef":{"DataFrameRef":{"value":"2016-11-15"},"DatedVehicleJourneyRef":"1956"},"OperatorRef":{"value":"HSL"},"Monitored":true,"VehicleLocation":{"Longitude":24.99136,"Latitude":60.24106},"Bearing":44,"Delay":120,"MonitoredCall":{"Order":4},"VehicleRef":{"value":"H9164"}}},{"ValidUntilTime":1479233276102,"RecordedAtTime":1479233246102,"MonitoredVehicleJourney":{"LineRef":{"value":"3002A"},"DirectionRef":{"value":"1"},"FramedVehicleJourneyRef":{"DataFrameRef":{"value":"2016-11-15"},"DatedVehicleJourneyRef":"1956"},"OperatorRef":{"value":"HSL"},"Monitored":true,"VehicleLocation":{"Longitude":24.87559,"Latitude":60.22195},"Bearing":264,"Delay":0,"MonitoredCall":{"Order":5},"VehicleRef":{"value":"H8251"}}},{"ValidUntilTime":1479233278000,"RecordedAtTime":1479233248000,"MonitoredVehicleJourney":{"LineRef":{"value":"1005"},"DirectionRef":{"value":"2"},"FramedVehicleJourneyRef":{"DataFrameRef":{"value":"2016-11-15"},"DatedVehicleJourneyRef":"2028"},"OperatorRef":{"value":"HSL"},"Monitored":true,"VehicleLocation":{"Longitude":24.922902,"Latitude":60.183993},"Bearing":0,"Delay":0,"MonitoredCall":{"Order":1},"VehicleRef":{"value":"RHKL00078"}}},{"ValidUntilTime":1479233275991,"RecordedAtTime":1479233245991,"MonitoredVehicleJourney":{"LineRef":{"value":"3002E"},"DirectionRef":{"value":"1"},"FramedVehicleJourneyRef":{"DataFrameRef":{"value":"2016-11-15"},"DatedVehicleJourneyRef":"1957"},"OperatorRef":{"value":"HSL"},"Monitored":true,"VehicleLocation":{"Longitude":24.83767,"Latitude":60.21942},"Bearing":241,"Delay":0,"MonitoredCall":{"Order":4},"VehicleRef":{"value":"H8391"}}},{"ValidUntilTime":1479233276206,"RecordedAtTime":1479233246206,"MonitoredVehicleJourney":{"LineRef":{"value":"3001R"},"DirectionRef":{"value":"2"},"FramedVehicleJourneyRef":{"DataFrameRef":{"value":"2016-11-15"},"DatedVehicleJourneyRef":"1955"},"OperatorRef":{"value":"HSL"},"Monitored":true,"VehicleLocation":{"Longitude":24.86607,"Latitude":60.62615},"Bearing":141,"Delay":60,"MonitoredCall":{"Order":3},"VehicleRef":{"value":"H9712"}}},{"ValidUntilTime":1479233276179,"RecordedAtTime":1479233246179,"MonitoredVehicleJourney":{"LineRef":{"value":"3002P"},"DirectionRef":{"value":"1"},"FramedVehicleJourneyRef":{"DataFrameRef":{"value":"2016-11-15"},"DatedVehicleJourneyRef":"2001"},"OperatorRef":{"value":"HSL"},"Monitored":true,"VehicleLocation":{"Longitude":24.92216,"Latitude":60.20705},"Bearing":314,"Delay":0,"MonitoredCall":{"Order":3},"VehicleRef":{"value":"H8759"}}},{"ValidUntilTime":1479233276151,"RecordedAtTime":1479233246151,"MonitoredVehicleJourney":{"LineRef":{"value":"3001N"},"DirectionRef":{"value":"2"},"FramedVehicleJourneyRef":{"DataFrameRef":{"value":"2016-11-15"},"DatedVehicleJourneyRef":"2002"},"OperatorRef":{"value":"HSL"},"Monitored":true,"VehicleLocation":{"Longitude":25.07971,"Latitude":60.35312},"Bearing":193,"Delay":0,"MonitoredCall":{"Order":3},"VehicleRef":{"value":"H9570"}}},{"ValidUntilTime":1479233276161,"RecordedAtTime":1479233246161,"MonitoredVehicleJourney":{"LineRef":{"value":"3001N"},"DirectionRef":{"value":"1"},"FramedVehicleJourneyRef":{"DataFrameRef":{"value":"2016-11-15"},"DatedVehicleJourneyRef":"2003"},"OperatorRef":{"value":"HSL"},"Monitored":true,"VehicleLocation":{"Longitude":24.93466,"Latitude":60.19879},"Bearing":24,"Delay":0,"MonitoredCall":{"Order":2},"VehicleRef":{"value":"H9577"}}}]}]}}}